Workbook

Sheet 计算口径
A1: 项目 | B1: 当前口径
A2: 初始资金 | B2: 20000
A3: 简单难度 | B3: 李言闻1000文/节气；每天2次妙手回春
A4: 普通难度 | B4: 李言闻500文/节气；每天3次妙手回春
A5: 困难难度 | B5: 李言闻0文/节气；每天4次妙手回春
A6: 第一年立春 | B6: 剧情跳过，无普通随机NPC诊疗
A7: 妙手回春 | B7: 每人名望+10、心得+1
A8: 药材净收入预期 | B8: 按每名随机病人生成时的已解锁疾病/方剂池动态计算；不再固定使用106.90625文/次
A9: 病家谢仪期望 | B9: 115.2
A10: 田租 | B10: 大暑+5000文；霜降+15000文
A11: 李建中俸禄 | B11: 按用户要求不触发
A12: 004_02 老师 | B12: 银钱0、名望0、心得0
A13: 005_02 世子 | B13: 银钱+1000、名望+1000、心得0；night_end结算
A14: 谢飞燕两次治疗 | B14: 023_02 +1000文；024_02 +1000文；合计+2000文
A15: 024_04 王百堂 | B15: 心得+7，影响后续条目/剧情解锁时间
A16: 方剂解锁假设 | B16: 药材条目达到心得阈值后及时阅读；药材齐全即解锁方剂及对应疾病
A17: 同节气内动态更新 | B17: 每次妙手回春+1心得，下一名random NPC立即按新解锁池计算期望药材收益
A18: 022_02 敬亭 | B18: 银钱+1000；按本次用户要求加入（当前项目数据中的人物名为柳敬亭）

Sheet 剧情奖励核对
A1: 剧情ID | B1: 剧情 | C1: 银钱 | D1: 名望 | E1: 心得 | F1: GitHub current main | G1: 说明
A2: 005_02 | B2: 治愈世子 | C2: 1000 | D2: 1000 | E2: 0 | F2: https://github.com/lqc19891229/Doctor/blob/main/Data/Story/005_02.tres | G2: night_end；+1000名望从下一节气普通诊费开始产生完整影响
A3: 014_02 | B3: 沈修文治疗成功 | C3: 1000 | D3: 0 | E3: 0 | F3: https://github.com/lqc19891229/Doctor/blob/main/Data/Story/014_02.tres | G3: 前置剧情链满足且心脾两虚已解锁后触发
A4: 017_02 | B4: 杨善泉治疗成功 | C4: 1000 | D4: 0 | E4: 0 | F4: https://github.com/lqc19891229/Doctor/blob/main/Data/Story/017_02.tres | G4: 前置剧情链满足且肾气不固已解锁后触发
A5: 022_02 | B5: 敬亭治疗成功 | C5: 1000 | D5: 0 | E5: 0 | F5: 用户本次指定（待同步项目数据） | G5: 用户要求加入+1000文；当前项目数据人物为柳敬亭（liu_jing_ting）
A6: 023_02 | B6: 谢飞燕肺气虚治疗成功 | C6: 1000 | D6: 0 | E6: 0 | F6: https://github.com/lqc19891229/Doctor/blob/main/Data/Story/023_02.tres | G6: 谢飞燕第一笔1000文
A7: 024_02 | B7: 谢飞燕肺阴虚治疗成功 | C7: 1000 | D7: 0 | E7: 0 | F7: https://github.com/lqc19891229/Doctor/blob/main/Data/Story/024_02.tres | G7: 谢飞燕第二笔1000文
A8: 024_04 | B8: 王百堂来访 | C8: 0 | D8: 0 | E8: 7 | F8: https://github.com/lqc19891229/Doctor/blob/main/Data/Story/024_04.tres | G8: 无银钱，但+7心得会提前后续条目/剧情
A9: 025_02 | B9: 和尚肾精不足治疗成功 | C9: 2000 | D9: 0 | E9: 0 | F9: https://github.com/lqc19891229/Doctor/blob/main/Data/Story/025_02.tres | G9: 前两年内部分难度可触发

Sheet 简单
A1: 年份 | B1: 节气 | C1: 妙手回春次数 | D1: 李言闻收入 | E1: 诊费预期 | F1: 药材净收入预期 | G1: 谢仪预期 | H1: 田租 | I1: 剧情银钱奖励 | J1: 预期收入 | K1: 累计预期收入 | L1: 预期支出 | M1: 累计预期支出 | N1: 本节气收支差 | O1: 累计收支差 | P1: 含初始资金余额 | Q1: 节气末名望 | R1: 节气末心得 | S1: 剧情备注
A2: 1 | B2: 立春 | C2: 0 | D2: 0 | E2: 0 | F2: =IF(C2>=1,VLOOKUP(0+MAX(0,R2-0-C2)+0,药材收益口径!$H$2:$I$222,2,FALSE),0)+IF(C2>=2,VLOOKUP(0+MAX(0,R2-0-C2)+1,药材收益口径!$H$2:$I$222,2,FALSE),0)+IF(C2>=3,VLOOKUP(0+MAX(0,R2-0-C2)+2,药材收益口径!$H$2:$I$222,2,FALSE),0)+IF(C2>=4,VLOOKUP(0+MAX(0,R2-0-C2)+3,药材收益口径!$H$2:$I$222,2,FALSE),0) -> 0 | G2: 0 | H2: 0 | I2: 0 | J2: =SUM(D2:I2) -> 0 | K2: =J2 -> 0 | L2: =K2 -> 0 | M2: =L2 -> 0 | N2: =J2-L2 -> 0 | O2: =K2-M2 -> 0 | P2: =20000+O2 -> 20000 | Q2: 0 | R2: 0
A3: 1 | B3: 雨水 | C3: 2 | D3: 1000 | E3: 40 | F3: =IF(C3>=1,VLOOKUP(R2+MAX(0,R3-R2-C3)+0,药材收益口径!$H$2:$I$222,2,FALSE),0)+IF(C3>=2,VLOOKUP(R2+MAX(0,R3-R2-C3)+1,药材收益口径!$H$2:$I$222,2,FALSE),0)+IF(C3>=3,VLOOKUP(R2+MAX(0,R3-R2-C3)+2,药材收益口径!$H$2:$I$222,2,FALSE),0)+IF(C3>=4,VLOOKUP(R2+MAX(0,R3-R2-C3)+3,药材收益口径!$H$2:$I$222,2,FALSE),0) -> 39.333333 | G3: 230.4 | H3: 0 | I3: 0 | J3: =SUM(D3:I3) -> 1309.7333 | K3: =K2+J3 -> 1309.7333 | L3: 2776.4 | M3: =M2+L3 -> 2776.4 | N3: =J3-L3 -> -1466.6667 | O3: =K3-M3 -> -1466.6667 | P3: =20000+O3 -> 18533.333 | Q3: 20 | R3: 2
A4: 1 | B4: 惊蛰 | C4: 2 | D4: 1000 | E4: 40 | F4: =IF(C4>=1,VLOOKUP(R3+MAX(0,R4-R3-C4)+0,药材收益口径!$H$2:$I$222,2,FALSE),0)+IF(C4>=2,VLOOKUP(R3+MAX(0,R4-R3-C4)+1,药材收益口径!$H$2:$I$222,2,FALSE),0)+IF(C4>=3,VLOOKUP(R3+MAX(0,R4-R3-C4)+2,药材收益口径!$H$2:$I$222,2,FALSE),0)+IF(C4>=4,VLOOKUP(R3+MAX(0,R4-R3-C4)+3,药材收益口径!$H$2:$I$222,2,FALSE),0) -> 39.333333 | G4: 230.4 | H4: 0 | I4: 0 | J4: =SUM(D4:I4) -> 1309.7333 | K4: =K3+J4 -> 2619.4667 | L4: 1550 | M4: =M3+L4 -> 4326.4 | N4: =J4-L4 -> -240.26667 | O4: =K4-M4 -> -1706.9333 | P4: =20000+O4 -> 18293.067 | Q4: 40 | R4: 4
A5: 1 | B5: 春分 | C5: 2 | D5: 1000 | E5: 40 | F5: =IF(C5>=1,VLOOKUP(R4+MAX(0,R5-R4-C5)+0,药材收益口径!$H$2:$I$222,2,FALSE),0)+IF(C5>=2,VLOOKUP(R4+MAX(0,R5-R4-C5)+1,药材收益口径!$H$2:$I$222,2,FALSE),0)+IF(C5>=3,VLOOKUP(R4+MAX(0,R5-R4-C5)+2,药材收益口径!$H$2:$I$222,2,FALSE),0)+IF(C5>=4,VLOOKUP(R4+MAX(0,R5-R4-C5)+3,药材收益口径!$H$2:$I$222,2,FALSE),0) -> 39.333333 | G5: 230.4 | H5: 0 | I5: 0 | J5: =SUM(D5:I5) -> 1309.7333 | K5: =K4+J5 -> 3929.2 | L5: 3376.4 | M5: =M4+L5 -> 7702.8 | N5: =J5-L5 -> -2066.6667 | O5: =K5-M5 -> -3773.6 | P5: =20000+O5 -> 16226.4 | Q5: 60 | R5: 6
A6: 1 | B6: 清明 | C6: 2 | D6: 1000 | E6: 40 | F6: =IF(C6>=1,VLOOKUP(R5+MAX(0,R6-R5-C6)+0,药材收益口径!$H$2:$I$222,2,FALSE),0)+IF(C6>=2,VLOOKUP(R5+MAX(0,R6-R5-C6)+1,药材收益口径!$H$2:$I$222,2,FALSE),0)+IF(C6>=3,VLOOKUP(R5+MAX(0,R6-R5-C6)+2,药材收益口径!$H$2:$I$222,2,FALSE),0)+IF(C6>=4,VLOOKUP(R5+MAX(0,R6-R5-C6)+3,药材收益口径!$H$2:$I$222,2,FALSE),0) -> 39.333333 | G6: 230.4 | H6: 0 | I6: 0 | J6: =SUM(D6:I6) -> 1309.7333 | K6: =K5+J6 -> 5238.9333 | L6: 3550 | M6: =M5+L6 -> 11252.8 | N6: =J6-L6 -> -2240.2667 | O6: =K6-M6 -> -6013.8667 | P6: =20000+O6 -> 13986.133 | Q6: 80 | R6: 8
A7: 1 | B7: 谷雨 | C7: 2 | D7: 1000 | E7: 40 | F7: =IF(C7>=1,VLOOKUP(R6+MAX(0,R7-R6-C7)+0,药材收益口径!$H$2:$I$222,2,FALSE),0)+IF(C7>=2,VLOOKUP(R6+MAX(0,R7-R6-C7)+1,药材收益口径!$H$2:$I$222,2,FALSE),0)+IF(C7>=3,VLOOKUP(R6+MAX(0,R7-R6-C7)+2,药材收益口径!$H$2:$I$222,2,FALSE),0)+IF(C7>=4,VLOOKUP(R6+MAX(0,R7-R6-C7)+3,药材收益口径!$H$2:$I$222,2,FALSE),0) -> 88.916667 | G7: 230.4 | H7: 0 | I7: 0 | J7: =SUM(D7:I7) -> 1359.3167 | K7: =K6+J7 -> 6598.25 | L7: 2776.4 | M7: =M6+L7 -> 14029.2 | N7: =J7-L7 -> -1417.0833 | O7: =K7-M7 -> -7430.95 | P7: =20000+O7 -> 12569.05 | Q7: 100 | R7: 10
A8: 1 | B8: 立夏 | C8: 2 | D8: 1000 | E8: 70 | F8: =IF(C8>=1,VLOOKUP(R7+MAX(0,R8-R7-C8)+0,药材收益口径!$H$2:$I$222,2,FALSE),0)+IF(C8>=2,VLOOKUP(R7+MAX(0,R8-R7-C8)+1,药材收益口径!$H$2:$I$222,2,FALSE),0)+IF(C8>=3,VLOOKUP(R7+MAX(0,R8-R7-C8)+2,药材收益口径!$H$2:$I$222,2,FALSE),0)+IF(C8>=4,VLOOKUP(R7+MAX(0,R8-R7-C8)+3,药材收益口径!$H$2:$I$222,2,FALSE),0) -> 138.5 | G8: 230.4 | H8: 0 | I8: 0 | J8: =SUM(D8:I8) -> 1438.9 | K8: =K7+J8 -> 8037.15 | L8: 2650 | M8: =M7+L8 -> 16679.2 | N8: =J8-L8 -> -1211.1 | O8: =K8-M8 -> -8642.05 | P8: =20000+O8 -> 11357.95 | Q8: 120 | R8: 12
A9: 1 | B9: 小满 | C9: 2 | D9: 1000 | E9: 100 | F9: =IF(C9>=1,VLOOKUP(R8+MAX(0,R9-R8-C9)+0,药材收益口径!$H$2:$I$222,2,FALSE),0)+IF(C9>=2,VLOOKUP(R8+MAX(0,R9-R8-C9)+1,药材收益口径!$H$2:$I$222,2,FALSE),0)+IF(C9>=3,VLOOKUP(R8+MAX(0,R9-R8-C9)+2,药材收益口径!$H$2:$I$222,2,FALSE),0)+IF(C9>=4,VLOOKUP(R8+MAX(0,R9-R8-C9)+3,药材收益口径!$H$2:$I$222,2,FALSE),0) -> 138.5 | G9: 230.4 | H9: 0 | I9: 0 | J9: =SUM(D9:I9) -> 1468.9 | K9: =K8+J9 -> 9506.05 | L9: 3676.4 | M9: =M8+L9 -> 20355.6 | N9: =J9-L9 -> -2207.5 | O9: =K9-M9 -> -10849.55 | P9: =20000+O9 -> 9150.45 | Q9: 140 | R9: 14
A10: 1 | B10: 芒种 | C10: 2 | D10: 1000 | E10: 100 | F10: =IF(C10>=1,VLOOKUP(R9+MAX(0,R10-R9-C10)+0,药材收益口径!$H$2:$I$222,2,FALSE),0)+IF(C10>=2,VLOOKUP(R9+MAX(0,R10-R9-C10)+1,药材收益口径!$H$2:$I$222,2,FALSE),0)+IF(C10>=3,VLOOKUP(R9+MAX(0,R10-R9-C10)+2,药材收益口径!$H$2:$I$222,2,FALSE),0)+IF(C10>=4,VLOOKUP(R9+MAX(0,R10-R9-C10)+3,药材收益口径!$H$2:$I$222,2,FALSE),0) -> 122.6 | G10: 230.4 | H10: 0 | I10: 1000 | J10: =SUM(D10:I10) -> 2453 | K10: =K9+J10 -> 11959.05 | L10: 2450 | M10: =M9+L10 -> 22805.6 | N10: =J10-L10 -> 3 | O10: =K10-M10 -> -10846.55 | P10: =20000+O10 -> 9153.45 | Q10: 160 | R10: 16 | S10: 022_02 敬亭治疗成功（银钱+1000）
A11: 1 | B11: 夏至 | C11: 2 | D11: 1000 | E11: 100 | F11: =IF(C11>=1,VLOOKUP(R10+MAX(0,R11-R10-C11)+0,药材收益口径!$H$2:$I$222,2,FALSE),0)+IF(C11>=2,VLOOKUP(R10+MAX(0,R11-R10-C11)+1,药材收益口径!$H$2:$I$222,2,FALSE),0)+IF(C11>=3,VLOOKUP(R10+MAX(0,R11-R10-C11)+2,药材收益口径!$H$2:$I$222,2,FALSE),0)+IF(C11>=4,VLOOKUP(R10+MAX(0,R11-R10-C11)+3,药材收益口径!$H$2:$I$222,2,FALSE),0) -> 122.6 | G11: 230.4 | H11: 0 | I11: 0 | J11: =SUM(D11:I11) -> 1453 | K11: =K10+J11 -> 13412.05 | L11: 3676.4 | M11: =M10+L11 -> 26482 | N11: =J11-L11 -> -2223.4 | O11: =K11-M11 -> -13069.95 | P11: =20000+O11 -> 6930.05 | Q11: 180 | R11: 18
A12: 1 | B12: 小暑 | C12: 2 | D12: 1000 | E12: 100 | F12: =IF(C12>=1,VLOOKUP(R11+MAX(0,R12-R11-C12)+0,药材收益口径!$H$2:$I$222,2,FALSE),0)+IF(C12>=2,VLOOKUP(R11+MAX(0,R12-R11-C12)+1,药材收益口径!$H$2:$I$222,2,FALSE),0)+IF(C12>=3,VLOOKUP(R11+MAX(0,R12-R11-C12)+2,药材收益口径!$H$2:$I$222,2,FALSE),0)+IF(C12>=4,VLOOKUP(R11+MAX(0,R12-R11-C12)+3,药材收益口径!$H$2:$I$222,2,FALSE),0) -> 119.38333 | G12: 230.4 | H12: 0 | I12: 0 | J12: =SUM(D12:I12) -> 1449.7833 | K12: =K11+J12 -> 14861.833 | L12: 2450 | M12: =M11+L12 -> 28932 | N12: =J12-L12 -> -1000.2167 | O12: =K12-M12 -> -14070.167 | P12: =20000+O12 -> 5929.8333 | Q12: 200 | R12: 20
A13: 1 | B13: 大暑 | C13: 2 | D13: 1000 | E13: 100 | F13: =IF(C13>=1,VLOOKUP(R12+MAX(0,R13-R12-C13)+0,药材收益口径!$H$2:$I$222,2,FALSE),0)+IF(C13>=2,VLOOKUP(R12+MAX(0,R13-R12-C13)+1,药材收益口径!$H$2:$I$222,2,FALSE),0)+IF(C13>=3,VLOOKUP(R12+MAX(0,R13-R12-C13)+2,药材收益口径!$H$2:$I$222,2,FALSE),0)+IF(C13>=4,VLOOKUP(R12+MAX(0,R13-R12-C13)+3,药材收益口径!$H$2:$I$222,2,FALSE),0) -> 119 | G13: 230.4 | H13: 5000 | I13: 0 | J13: =SUM(D13:I13) -> 6449.4 | K13: =K12+J13 -> 21311.233 | L13: 3276.4 | M13: =M12+L13 -> 32208.4 | N13: =J13-L13 -> 3173 | O13: =K13-M13 -> -10897.167 | P13: =20000+O13 -> 9102.8333 | Q13: 220 | R13: 22
A14: 1 | B14: 立秋 | C14: 2 | D14: 1000 | E14: 100 | F14: =IF(C14>=1,VLOOKUP(R13+MAX(0,R14-R13-C14)+0,药材收益口径!$H$2:$I$222,2,FALSE),0)+IF(C14>=2,VLOOKUP(R13+MAX(0,R14-R13-C14)+1,药材收益口径!$H$2:$I$222,2,FALSE),0)+IF(C14>=3,VLOOKUP(R13+MAX(0,R14-R13-C14)+2,药材收益口径!$H$2:$I$222,2,FALSE),0)+IF(C14>=4,VLOOKUP(R13+MAX(0,R14-R13-C14)+3,药材收益口径!$H$2:$I$222,2,FALSE),0) -> 124.0625 | G14: 230.4 | H14: 0 | I14: 0 | J14: =SUM(D14:I14) -> 1454.4625 | K14: =K13+J14 -> 22765.696 | L14: 2650 | M14: =M13+L14 -> 34858.4 | N14: =J14-L14 -> -1195.5375 | O14: =K14-M14 -> -12092.704 | P14: =20000+O14 -> 7907.2958 | Q14: 240 | R14: 24
A15: 1 | B15: 处暑 | C15: 2 | D15: 1000 | E15: 100 | F15: =IF(C15>=1,VLOOKUP(R14+MAX(0,R15-R14-C15)+0,药材收益口径!$H$2:$I$222,2,FALSE),0)+IF(C15>=2,VLOOKUP(R14+MAX(0,R15-R14-C15)+1,药材收益口径!$H$2:$I$222,2,FALSE),0)+IF(C15>=3,VLOOKUP(R14+MAX(0,R15-R14-C15)+2,药材收益口径!$H$2:$I$222,2,FALSE),0)+IF(C15>=4,VLOOKUP(R14+MAX(0,R15-R14-C15)+3,药材收益口径!$H$2:$I$222,2,FALSE),0) -> 198.39583 | G15: 230.4 | H15: 0 | I15: 0 | J15: =SUM(D15:I15) -> 1528.7958 | K15: =K14+J15 -> 24294.492 | L15: 4776.4 | M15: =M14+L15 -> 39634.8 | N15: =J15-L15 -> -3247.6042 | O15: =K15-M15 -> -15340.308 | P15: =20000+O15 -> 4659.6917 | Q15: 260 | R15: 26
A16: 1 | B16: 白露 | C16: 2 | D16: 1000 | E16: 100 | F16: =IF(C16>=1,VLOOKUP(R15+MAX(0,R16-R15-C16)+0,药材收益口径!$H$2:$I$222,2,FALSE),0)+IF(C16>=2,VLOOKUP(R15+MAX(0,R16-R15-C16)+1,药材收益口径!$H$2:$I$222,2,FALSE),0)+IF(C16>=3,VLOOKUP(R15+MAX(0,R16-R15-C16)+2,药材收益口径!$H$2:$I$222,2,FALSE),0)+IF(C16>=4,VLOOKUP(R15+MAX(0,R16-R15-C16)+3,药材收益口径!$H$2:$I$222,2,FALSE),0) -> 234.27273 | G16: 230.4 | H16: 0 | I16: 0 | J16: =SUM(D16:I16) -> 1564.6727 | K16: =K15+J16 -> 25859.164 | L16: 1550 | M16: =M15+L16 -> 41184.8 | N16: =J16-L16 -> 14.672727 | O16: =K16-M16 -> -15325.636 | P16: =20000+O16 -> 4674.3644 | Q16: 280 | R16: 28
A17: 1 | B17: 秋分 | C17: 2 | D17: 1000 | E17: 100 | F17: =IF(C17>=1,VLOOKUP(R16+MAX(0,R17-R16-C17)+0,药材收益口径!$H$2:$I$222,2,FALSE),0)+IF(C17>=2,VLOOKUP(R16+MAX(0,R17-R16-C17)+1,药材收益口径!$H$2:$I$222,2,FALSE),0)+IF(C17>=3,VLOOKUP(R16+MAX(0,R17-R16-C17)+2,药材收益口径!$H$2:$I$222,2,FALSE),0)+IF(C17>=4,VLOOKUP(R16+MAX(0,R17-R16-C17)+3,药材收益口径!$H$2:$I$222,2,FALSE),0) -> 215.46154 | G17: 230.4 | H17: 0 | I17: 0 | J17: =SUM(D17:I17) -> 1545.8615 | K17: =K16+J17 -> 27405.026 | L17: 3376.4 | M17: =M16+L17 -> 44561.2 | N17: =J17-L17 -> -1830.5385 | O17: =K17-M17 -> -17156.174 | P17: =20000+O17 -> 2843.8259 | Q17: 300 | R17: 30
A18: 1 | B18: 寒露 | C18: 2 | D18: 1000 | E18: 250 | F18: =IF(C18>=1,VLOOKUP(R17+MAX(0,R18-R17-C18)+0,药材收益口径!$H$2:$I$222,2,FALSE),0)+IF(C18>=2,VLOOKUP(R17+MAX(0,R18-R17-C18)+1,药材收益口径!$H$2:$I$222,2,FALSE),0)+IF(C18>=3,VLOOKUP(R17+MAX(0,R18-R17-C18)+2,药材收益口径!$H$2:$I$222,2,FALSE),0)+IF(C18>=4,VLOOKUP(R17+MAX(0,R18-R17-C18)+3,药材收益口径!$H$2:$I$222,2,FALSE),0) -> 215.46154 | G18: 230.4 | H18: 0 | I18: 0 | J18: =SUM(D18:I18) -> 1695.8615 | K18: =K17+J18 -> 29100.887 | L18: 1550 | M18: =M17+L18 -> 46111.2 | N18: =J18-L18 -> 145.86154 | O18: =K18-M18 -> -17010.313 | P18: =20000+O18 -> 2989.6875 | Q18: 320 | R18: 32
A19: 1 | B19: 霜降 | C19: 2 | D19: 1000 | E19: 400 | F19: =IF(C19>=1,VLOOKUP(R18+MAX(0,R19-R18-C19)+0,药材收益口径!$H$2:$I$222,2,FALSE),0)+IF(C19>=2,VLOOKUP(R18+MAX(0,R19-R18-C19)+1,药材收益口径!$H$2:$I$222,2,FALSE),0)+IF(C19>=3,VLOOKUP(R18+MAX(0,R19-R18-C19)+2,药材收益口径!$H$2:$I$222,2,FALSE),0)+IF(C19>=4,VLOOKUP(R18+MAX(0,R19-R18-C19)+3,药材收益口径!$H$2:$I$222,2,FALSE),0) -> 213.98077 | G19: 230.4 | H19: 15000 | I19: 0 | J19: =SUM(D19:I19) -> 16844.381 | K19: =K18+J19 -> 45945.268 | L19: 4276.4 | M19: =M18+L19 -> 50387.6 | N19: =J19-L19 -> 12567.981 | O19: =K19-M19 -> -4442.3318 | P19: =20000+O19 -> 15557.668 | Q19: 340 | R19: 34
A20: 1 | B20: 立冬 | C20: 2 | D20: 1000 | E20: 400 | F20: =IF(C20>=1,VLOOKUP(R19+MAX(0,R20-R19-C20)+0,药材收益口径!$H$2:$I$222,2,FALSE),0)+IF(C20>=2,VLOOKUP(R19+MAX(0,R20-R19-C20)+1,药材收益口径!$H$2:$I$222,2,FALSE),0)+IF(C20>=3,VLOOKUP(R19+MAX(0,R20-R19-C20)+2,药材收益口径!$H$2:$I$222,2,FALSE),0)+IF(C20>=4,VLOOKUP(R19+MAX(0,R20-R19-C20)+3,药材收益口径!$H$2:$I$222,2,FALSE),0) -> 210.35 | G20: 230.4 | H20: 0 | I20: 0 | J20: =SUM(D20:I20) -> 1840.75 | K20: =K19+J20 -> 47786.018 | L20: 4750 | M20: =M19+L20 -> 55137.6 | N20: =J20-L20 -> -2909.25 | O20: =K20-M20 -> -7351.5818 | P20: =20000+O20 -> 12648.418 | Q20: 360 | R20: 36
A21: 1 | B21: 小雪 | C21: 2 | D21: 1000 | E21: 400 | F21: =IF(C21>=1,VLOOKUP(R20+MAX(0,R21-R20-C21)+0,药材收益口径!$H$2:$I$222,2,FALSE),0)+IF(C21>=2,VLOOKUP(R20+MAX(0,R21-R20-C21)+1,药材收益口径!$H$2:$I$222,2,FALSE),0)+IF(C21>=3,VLOOKUP(R20+MAX(0,R21-R20-C21)+2,药材收益口径!$H$2:$I$222,2,FALSE),0)+IF(C21>=4,VLOOKUP(R20+MAX(0,R21-R20-C21)+3,药材收益口径!$H$2:$I$222,2,FALSE),0) -> 210.40625 | G21: 230.4 | H21: 0 | I21: 0 | J21: =SUM(D21:I21) -> 1840.8063 | K21: =K20+J21 -> 49626.824 | L21: 2776.4 | M21: =M20+L21 -> 57914 | N21: =J21-L21 -> -935.59375 | O21: =K21-M21 -> -8287.1755 | P21: =20000+O21 -> 11712.824 | Q21: 380 | R21: 38
A22: 1 | B22: 大雪 | C22: 2 | D22: 1000 | E22: 400 | F22: =IF(C22>=1,VLOOKUP(R21+MAX(0,R22-R21-C22)+0,药材收益口径!$H$2:$I$222,2,FALSE),0)+IF(C22>=2,VLOOKUP(R21+MAX(0,R22-R21-C22)+1,药材收益口径!$H$2:$I$222,2,FALSE),0)+IF(C22>=3,VLOOKUP(R21+MAX(0,R22-R21-C22)+2,药材收益口径!$H$2:$I$222,2,FALSE),0)+IF(C22>=4,VLOOKUP(R21+MAX(0,R22-R21-C22)+3,药材收益口径!$H$2:$I$222,2,FALSE),0) -> 207 | G22: 230.4 | H22: 0 | I22: 0 | J22: =SUM(D22:I22) -> 1837.4 | K22: =K21+J22 -> 51464.224 | L22: 1550 | M22: =M21+L22 -> 59464 | N22: =J22-L22 -> 287.4 | O22: =K22-M22 -> -7999.7755 | P22: =20000+O22 -> 12000.224 | Q22: 400 | R22: 40
A23: 1 | B23: 冬至 | C23: 2 | D23: 1000 | E23: 400 | F23: =IF(C23>=1,VLOOKUP(R22+MAX(0,R23-R22-C23)+0,药材收益口径!$H$2:$I$222,2,FALSE),0)+IF(C23>=2,VLOOKUP(R22+MAX(0,R23-R22-C23)+1,药材收益口径!$H$2:$I$222,2,FALSE),0)+IF(C23>=3,VLOOKUP(R22+MAX(0,R23-R22-C23)+2,药材收益口径!$H$2:$I$222,2,FALSE),0)+IF(C23>=4,VLOOKUP(R22+MAX(0,R23-R22-C23)+3,药材收益口径!$H$2:$I$222,2,FALSE),0) -> 214.94444 | G23: 230.4 | H23: 0 | I23: 1000 | J23: =SUM(D23:I23) -> 2845.3444 | K23: =K22+J23 -> 54309.569 | L23: 2776.4 | M23: =M22+L23 -> 62240.4 | N23: =J23-L23 -> 68.944444 | O23: =K23-M23 -> -7930.8311 | P23: =20000+O23 -> 12069.169 | Q23: 420 | R23: 42 | S23: 023_02 谢飞燕肺气虚（银钱+1000）
A24: 1 | B24: 小寒 | C24: 2 | D24: 1000 | E24: 400 | F24: =IF(C24>=1,VLOOKUP(R23+MAX(0,R24-R23-C24)+0,药材收益口径!$H$2:$I$222,2,FALSE),0)+IF(C24>=2,VLOOKUP(R23+MAX(0,R24-R23-C24)+1,药材收益口径!$H$2:$I$222,2,FALSE),0)+IF(C24>=3,VLOOKUP(R23+MAX(0,R24-R23-C24)+2,药材收益口径!$H$2:$I$222,2,FALSE),0)+IF(C24>=4,VLOOKUP(R23+MAX(0,R24-R23-C24)+3,药材收益口径!$H$2:$I$222,2,FALSE),0) -> 214.94444 | G24: 230.4 | H24: 0 | I24: 0 | J24: =SUM(D24:I24) -> 1845.3444 | K24: =K23+J24 -> 56154.913 | L24: 1550 | M24: =M23+L24 -> 63790.4 | N24: =J24-L24 -> 295.34444 | O24: =K24-M24 -> -7635.4866 | P24: =20000+O24 -> 12364.513 | Q24: 440 | R24: 44
A25: 1 | B25: 大寒 | C25: 2 | D25: 1000 | E25: 400 | F25: =IF(C25>=1,VLOOKUP(R24+MAX(0,R25-R24-C25)+0,药材收益口径!$H$2:$I$222,2,FALSE),0)+IF(C25>=2,VLOOKUP(R24+MAX(0,R25-R24-C25)+1,药材收益口径!$H$2:$I$222,2,FALSE),0)+IF(C25>=3,VLOOKUP(R24+MAX(0,R25-R24-C25)+2,药材收益口径!$H$2:$I$222,2,FALSE),0)+IF(C25>=4,VLOOKUP(R24+MAX(0,R25-R24-C25)+3,药材收益口径!$H$2:$I$222,2,FALSE),0) -> 209.94737 | G25: 230.4 | H25: 0 | I25: 1000 | J25: =SUM(D25:I25) -> 2840.3474 | K25: =K24+J25 -> 58995.261 | L25: 3376.4 | M25: =M24+L25 -> 67166.8 | N25: =J25-L25 -> -536.05263 | O25: =K25-M25 -> -8171.5393 | P25: =20000+O25 -> 11828.461 | Q25: 460 | R25: 46 | S25: 024_02 谢飞燕肺阴虚（银钱+1000）
A26: 2 | B26: 立春 | C26: 2 | D26: 1000 | E26: 400 | F26: =IF(C26>=1,VLOOKUP(R25+MAX(0,R26-R25-C26)+0,药材收益口径!$H$2:$I$222,2,FALSE),0)+IF(C26>=2,VLOOKUP(R25+MAX(0,R26-R25-C26)+1,药材收益口径!$H$2:$I$222,2,FALSE),0)+IF(C26>=3,VLOOKUP(R25+MAX(0,R26-R25-C26)+2,药材收益口径!$H$2:$I$222,2,FALSE),0)+IF(C26>=4,VLOOKUP(R25+MAX(0,R26-R25-C26)+3,药材收益口径!$H$2:$I$222,2,FALSE),0) -> 209.94737 | G26: 230.4 | H26: 0 | I26: 0 | J26: =SUM(D26:I26) -> 1840.3474 | K26: =K25+J26 -> 60835.608 | L26: 2650 | M26: =M25+L26 -> 69816.8 | N26: =J26-L26 -> -809.65263 | O26: =K26-M26 -> -8981.1919 | P26: =20000+O26 -> 11018.808 | Q26: 480 | R26: 48
A27: 2 | B27: 雨水 | C27: 2 | D27: 1000 | E27: 400 | F27: =IF(C27>=1,VLOOKUP(R26+MAX(0,R27-R26-C27)+0,药材收益口径!$H$2:$I$222,2,FALSE),0)+IF(C27>=2,VLOOKUP(R26+MAX(0,R27-R26-C27)+1,药材收益口径!$H$2:$I$222,2,FALSE),0)+IF(C27>=3,VLOOKUP(R26+MAX(0,R27-R26-C27)+2,药材收益口径!$H$2:$I$222,2,FALSE),0)+IF(C27>=4,VLOOKUP(R26+MAX(0,R27-R26-C27)+3,药材收益口径!$H$2:$I$222,2,FALSE),0) -> 243.27262 | G27: 230.4 | H27: 0 | I27: 0 | J27: =SUM(D27:I27) -> 1873.6726 | K27: =K26+J27 -> 62709.281 | L27: 2776.4 | M27: =M26+L27 -> 72593.2 | N27: =J27-L27 -> -902.72738 | O27: =K27-M27 -> -9883.9193 | P27: =20000+O27 -> 10116.081 | Q27: 500 | R27: 50
A28: 2 | B28: 惊蛰 | C28: 2 | D28: 1000 | E28: 400 | F28: =IF(C28>=1,VLOOKUP(R27+MAX(0,R28-R27-C28)+0,药材收益口径!$H$2:$I$222,2,FALSE),0)+IF(C28>=2,VLOOKUP(R27+MAX(0,R28-R27-C28)+1,药材收益口径!$H$2:$I$222,2,FALSE),0)+IF(C28>=3,VLOOKUP(R27+MAX(0,R28-R27-C28)+2,药材收益口径!$H$2:$I$222,2,FALSE),0)+IF(C28>=4,VLOOKUP(R27+MAX(0,R28-R27-C28)+3,药材收益口径!$H$2:$I$222,2,FALSE),0) -> 247.47917 | G28: 230.4 | H28: 0 | I28: 1000 | J28: =SUM(D28:I28) -> 2877.8792 | K28: =K27+J28 -> 65587.16 | L28: 1550 | M28: =M27+L28 -> 74143.2 | N28: =J28-L28 -> 1327.8792 | O28: =K28-M28 -> -8556.0401 | P28: =20000+O28 -> 11443.96 | Q28: 1520 | R28: 59 | S28: 024_04 王百堂来访（心得+7）；005_02 治愈世子（银钱+1000，名望+1000）
A29: 2 | B29: 春分 | C29: 2 | D29: 1000 | E29: 1000 | F29: =IF(C29>=1,VLOOKUP(R28+MAX(0,R29-R28-C29)+0,药材收益口径!$H$2:$I$222,2,FALSE),0)+IF(C29>=2,VLOOKUP(R28+MAX(0,R29-R28-C29)+1,药材收益口径!$H$2:$I$222,2,FALSE),0)+IF(C29>=3,VLOOKUP(R28+MAX(0,R29-R28-C29)+2,药材收益口径!$H$2:$I$222,2,FALSE),0)+IF(C29>=4,VLOOKUP(R28+MAX(0,R29-R28-C29)+3,药材收益口径!$H$2:$I$222,2,FALSE),0) -> 240.17877 | G29: 230.4 | H29: 0 | I29: 0 | J29: =SUM(D29:I29) -> 2470.5788 | K29: =K28+J29 -> 68057.739 | L29: 3376.4 | M29: =M28+L29 -> 77519.6 | N29: =J29-L29 -> -905.82123 | O29: =K29-M29 -> -9461.8613 | P29: =20000+O29 -> 10538.139 | Q29: 1540 | R29: 61
A30: 2 | B30: 清明 | C30: 2 | D30: 1000 | E30: 1000 | F30: =IF(C30>=1,VLOOKUP(R29+MAX(0,R30-R29-C30)+0,药材收益口径!$H$2:$I$222,2,FALSE),0)+IF(C30>=2,VLOOKUP(R29+MAX(0,R30-R29-C30)+1,药材收益口径!$H$2:$I$222,2,FALSE),0)+IF(C30>=3,VLOOKUP(R29+MAX(0,R30-R29-C30)+2,药材收益口径!$H$2:$I$222,2,FALSE),0)+IF(C30>=4,VLOOKUP(R29+MAX(0,R30-R29-C30)+3,药材收益口径!$H$2:$I$222,2,FALSE),0) -> 235.54828 | G30: 230.4 | H30: 0 | I30: 0 | J30: =SUM(D30:I30) -> 2465.9483 | K30: =K29+J30 -> 70523.687 | L30: 3550 | M30: =M29+L30 -> 81069.6 | N30: =J30-L30 -> -1084.0517 | O30: =K30-M30 -> -10545.913 | P30: =20000+O30 -> 9454.087 | Q30: 1560 | R30: 63
A31: 2 | B31: 谷雨 | C31: 2 | D31: 1000 | E31: 1000 | F31: =IF(C31>=1,VLOOKUP(R30+MAX(0,R31-R30-C31)+0,药材收益口径!$H$2:$I$222,2,FALSE),0)+IF(C31>=2,VLOOKUP(R30+MAX(0,R31-R30-C31)+1,药材收益口径!$H$2:$I$222,2,FALSE),0)+IF(C31>=3,VLOOKUP(R30+MAX(0,R31-R30-C31)+2,药材收益口径!$H$2:$I$222,2,FALSE),0)+IF(C31>=4,VLOOKUP(R30+MAX(0,R31-R30-C31)+3,药材收益口径!$H$2:$I$222,2,FALSE),0) -> 234.39286 | G31: 230.4 | H31: 0 | I31: 0 | J31: =SUM(D31:I31) -> 2464.7929 | K31: =K30+J31 -> 72988.48 | L31: 2776.4 | M31: =M30+L31 -> 83846 | N31: =J31-L31 -> -311.60714 | O31: =K31-M31 -> -10857.52 | P31: =20000+O31 -> 9142.4798 | Q31: 1580 | R31: 65
A32: 2 | B32: 立夏 | C32: 2 | D32: 1000 | E32: 1000 | F32: =IF(C32>=1,VLOOKUP(R31+MAX(0,R32-R31-C32)+0,药材收益口径!$H$2:$I$222,2,FALSE),0)+IF(C32>=2,VLOOKUP(R31+MAX(0,R32-R31-C32)+1,药材收益口径!$H$2:$I$222,2,FALSE),0)+IF(C32>=3,VLOOKUP(R31+MAX(0,R32-R31-C32)+2,药材收益口径!$H$2:$I$222,2,FALSE),0)+IF(C32>=4,VLOOKUP(R31+MAX(0,R32-R31-C32)+3,药材收益口径!$H$2:$I$222,2,FALSE),0) -> 234.39286 | G32: 230.4 | H32: 0 | I32: 0 | J32: =SUM(D32:I32) -> 2464.7929 | K32: =K31+J32 -> 75453.273 | L32: 2650 | M32: =M31+L32 -> 86496 | N32: =J32-L32 -> -185.20714 | O32: =K32-M32 -> -11042.727 | P32: =20000+O32 -> 8957.2727 | Q32: 1600 | R32: 67
A33: 2 | B33: 小满 | C33: 2 | D33: 1000 | E33: 1000 | F33: =IF(C33>=1,VLOOKUP(R32+MAX(0,R33-R32-C33)+0,药材收益口径!$H$2:$I$222,2,FALSE),0)+IF(C33>=2,VLOOKUP(R32+MAX(0,R33-R32-C33)+1,药材收益口径!$H$2:$I$222,2,FALSE),0)+IF(C33>=3,VLOOKUP(R32+MAX(0,R33-R32-C33)+2,药材收益口径!$H$2:$I$222,2,FALSE),0)+IF(C33>=4,VLOOKUP(R32+MAX(0,R33-R32-C33)+3,药材收益口径!$H$2:$I$222,2,FALSE),0) -> 248.58621 | G33: 230.4 | H33: 0 | I33: 0 | J33: =SUM(D33:I33) -> 2478.9862 | K33: =K32+J33 -> 77932.259 | L33: 3676.4 | M33: =M32+L33 -> 90172.4 | N33: =J33-L33 -> -1197.4138 | O33: =K33-M33 -> -12240.141 | P33: =20000+O33 -> 7759.8589 | Q33: 1620 | R33: 69
A34: 2 | B34: 芒种 | C34: 2 | D34: 1000 | E34: 1000 | F34: =IF(C34>=1,VLOOKUP(R33+MAX(0,R34-R33-C34)+0,药材收益口径!$H$2:$I$222,2,FALSE),0)+IF(C34>=2,VLOOKUP(R33+MAX(0,R34-R33-C34)+1,药材收益口径!$H$2:$I$222,2,FALSE),0)+IF(C34>=3,VLOOKUP(R33+MAX(0,R34-R33-C34)+2,药材收益口径!$H$2:$I$222,2,FALSE),0)+IF(C34>=4,VLOOKUP(R33+MAX(0,R34-R33-C34)+3,药材收益口径!$H$2:$I$222,2,FALSE),0) -> 248.58621 | G34: 230.4 | H34: 0 | I34: 0 | J34: =SUM(D34:I34) -> 2478.9862 | K34: =K33+J34 -> 80411.245 | L34: 2450 | M34: =M33+L34 -> 92622.4 | N34: =J34-L34 -> 28.986207 | O34: =K34-M34 -> -12211.155 | P34: =20000+O34 -> 7788.8451 | Q34: 1640 | R34: 71
A35: 2 | B35: 夏至 | C35: 2 | D35: 1000 | E35: 1000 | F35: =IF(C35>=1,VLOOKUP(R34+MAX(0,R35-R34-C35)+0,药材收益口径!$H$2:$I$222,2,FALSE),0)+IF(C35>=2,VLOOKUP(R34+MAX(0,R35-R34-C35)+1,药材收益口径!$H$2:$I$222,2,FALSE),0)+IF(C35>=3,VLOOKUP(R34+MAX(0,R35-R34-C35)+2,药材收益口径!$H$2:$I$222,2,FALSE),0)+IF(C35>=4,VLOOKUP(R34+MAX(0,R35-R34-C35)+3,药材收益口径!$H$2:$I$222,2,FALSE),0) -> 246.43826 | G35: 230.4 | H35: 0 | I35: 0 | J35: =SUM(D35:I35) -> 2476.8383 | K35: =K34+J35 -> 82888.083 | L35: 3676.4 | M35: =M34+L35 -> 96298.8 | N35: =J35-L35 -> -1199.5617 | O35: =K35-M35 -> -13410.717 | P35: =20000+O35 -> 6589.2833 | Q35: 1660 | R35: 73
A36: 2 | B36: 小暑 | C36: 2 | D36: 1000 | E36: 1000 | F36: =IF(C36>=1,VLOOKUP(R35+MAX(0,R36-R35-C36)+0,药材收益口径!$H$2:$I$222,2,FALSE),0)+IF(C36>=2,VLOOKUP(R35+MAX(0,R36-R35-C36)+1,药材收益口径!$H$2:$I$222,2,FALSE),0)+IF(C36>=3,VLOOKUP(R35+MAX(0,R36-R35-C36)+2,药材收益口径!$H$2:$I$222,2,FALSE),0)+IF(C36>=4,VLOOKUP(R35+MAX(0,R36-R35-C36)+3,药材收益口径!$H$2:$I$222,2,FALSE),0) -> 244.29032 | G36: 230.4 | H36: 0 | I36: 0 | J36: =SUM(D36:I36) -> 2474.6903 | K36: =K35+J36 -> 85362.774 | L36: 2450 | M36: =M35+L36 -> 98748.8 | N36: =J36-L36 -> 24.690323 | O36: =K36-M36 -> -13386.026 | P36: =20000+O36 -> 6613.9737 | Q36: 1680 | R36: 75
A37: 2 | B37: 大暑 | C37: 2 | D37: 1000 | E37: 1000 | F37: =IF(C37>=1,VLOOKUP(R36+MAX(0,R37-R36-C37)+0,药材收益口径!$H$2:$I$222,2,FALSE),0)+IF(C37>=2,VLOOKUP(R36+MAX(0,R37-R36-C37)+1,药材收益口径!$H$2:$I$222,2,FALSE),0)+IF(C37>=3,VLOOKUP(R36+MAX(0,R37-R36-C37)+2,药材收益口径!$H$2:$I$222,2,FALSE),0)+IF(C37>=4,VLOOKUP(R36+MAX(0,R37-R36-C37)+3,药材收益口径!$H$2:$I$222,2,FALSE),0) -> 285.8982 | G37: 230.4 | H37: 5000 | I37: 0 | J37: =SUM(D37:I37) -> 7516.2982 | K37: =K36+J37 -> 92879.072 | L37: 3276.4 | M37: =M36+L37 -> 102025.2 | N37: =J37-L37 -> 4239.8982 | O37: =K37-M37 -> -9146.1281 | P37: =20000+O37 -> 10853.872 | Q37: 1700 | R37: 77
A38: 2 | B38: 立秋 | C38: 2 | D38: 1000 | E38: 1000 | F38: =IF(C38>=1,VLOOKUP(R37+MAX(0,R38-R37-C38)+0,药材收益口径!$H$2:$I$222,2,FALSE),0)+IF(C38>=2,VLOOKUP(R37+MAX(0,R38-R37-C38)+1,药材收益口径!$H$2:$I$222,2,FALSE),0)+IF(C38>=3,VLOOKUP(R37+MAX(0,R38-R37-C38)+2,药材收益口径!$H$2:$I$222,2,FALSE),0)+IF(C38>=4,VLOOKUP(R37+MAX(0,R38-R37-C38)+3,药材收益口径!$H$2:$I$222,2,FALSE),0) -> 291.09581 | G38: 230.4 | H38: 0 | I38: 0 | J38: =SUM(D38:I38) -> 2521.4958 | K38: =K37+J38 -> 95400.568 | L38: 2650 | M38: =M37+L38 -> 104675.2 | N38: =J38-L38 -> -128.50419 | O38: =K38-M38 -> -9274.6323 | P38: =20000+O38 -> 10725.368 | Q38: 1720 | R38: 79
A39: 2 | B39: 处暑 | C39: 2 | D39: 1000 | E39: 1000 | F39: =IF(C39>=1,VLOOKUP(R38+MAX(0,R39-R38-C39)+0,药材收益口径!$H$2:$I$222,2,FALSE),0)+IF(C39>=2,VLOOKUP(R38+MAX(0,R39-R38-C39)+1,药材收益口径!$H$2:$I$222,2,FALSE),0)+IF(C39>=3,VLOOKUP(R38+MAX(0,R39-R38-C39)+2,药材收益口径!$H$2:$I$222,2,FALSE),0)+IF(C39>=4,VLOOKUP(R38+MAX(0,R39-R38-C39)+3,药材收益口径!$H$2:$I$222,2,FALSE),0) -> 297.67647 | G39: 230.4 | H39: 0 | I39: 0 | J39: =SUM(D39:I39) -> 2528.0765 | K39: =K38+J39 -> 97928.644 | L39: 4776.4 | M39: =M38+L39 -> 109451.6 | N39: =J39-L39 -> -2248.3235 | O39: =K39-M39 -> -11522.956 | P39: =20000+O39 -> 8477.0442 | Q39: 1740 | R39: 81
A40: 2 | B40: 白露 | C40: 2 | D40: 1000 | E40: 1000 | F40: =IF(C40>=1,VLOOKUP(R39+MAX(0,R40-R39-C40)+0,药材收益口径!$H$2:$I$222,2,FALSE),0)+IF(C40>=2,VLOOKUP(R39+MAX(0,R40-R39-C40)+1,药材收益口径!$H$2:$I$222,2,FALSE),0)+IF(C40>=3,VLOOKUP(R39+MAX(0,R40-R39-C40)+2,药材收益口径!$H$2:$I$222,2,FALSE),0)+IF(C40>=4,VLOOKUP(R39+MAX(0,R40-R39-C40)+3,药材收益口径!$H$2:$I$222,2,FALSE),0) -> 297.17143 | G40: 230.4 | H40: 0 | I40: 0 | J40: =SUM(D40:I40) -> 2527.5714 | K40: =K39+J40 -> 100456.22 | L40: 1550 | M40: =M39+L40 -> 111001.6 | N40: =J40-L40 -> 977.57143 | O40: =K40-M40 -> -10545.384 | P40: =20000+O40 -> 9454.6156 | Q40: 1760 | R40: 83
... A48: 2 | B48: 小寒 | C48: 2 | D48: 1000 | E48: 1000 | F48: =IF(C48>=1,VLOOKUP(R47+MAX(0,R48-R47-C48)+0,药材收益口径!$H$2:$I$222,2,FALSE),0)+IF(C48>=2,VLOOKUP(R47+MAX(0,R48-R47-C48)+1,药材收益口径!$H$2:$I$222,2,FALSE),0)+IF(C48>=3,VLOOKUP(R47+MAX(0,R48-R47-C48)+2,药材收益口径!$H$2:$I$222,2,FALSE),0)+IF(C48>=4,VLOOKUP(R47+MAX(0,R48-R47-C48)+3,药材收益口径!$H$2:$I$222,2,FALSE),0) -> 291.18308 | G48: 230.4 | H48: 0 | I48: 0 | J48: =SUM(D48:I48) -> 2521.5831 | K48: =K47+J48 -> 135617.57 | L48: 1550 | M48: =M47+L48 -> 133607.2 | N48: =J48-L48 -> 971.58308 | O48: =K48-M48 -> 2010.3719 | P48: =20000+O48 -> 22010.372 | Q48: 1920 | R48: 99
A49: 2 | B49: 大寒 | C49: 2 | D49: 1000 | E49: 1000 | F49: =IF(C49>=1,VLOOKUP(R48+MAX(0,R49-R48-C49)+0,药材收益口径!$H$2:$I$222,2,FALSE),0)+IF(C49>=2,VLOOKUP(R48+MAX(0,R49-R48-C49)+1,药材收益口径!$H$2:$I$222,2,FALSE),0)+IF(C49>=3,VLOOKUP(R48+MAX(0,R49-R48-C49)+2,药材收益口径!$H$2:$I$222,2,FALSE),0)+IF(C49>=4,VLOOKUP(R48+MAX(0,R49-R48-C49)+3,药材收益口径!$H$2:$I$222,2,FALSE),0) -> 295.88889 | G49: 230.4 | H49: 0 | I49: 2000 | J49: =SUM(D49:I49) -> 4526.2889 | K49: =K48+J49 -> 140143.86 | L49: 3376.4 | M49: =M48+L49 -> 136983.6 | N49: =J49-L49 -> 1149.8889 | O49: =K49-M49 -> 3160.2608 | P49: =20000+O49 -> 23160.261 | Q49: 1940 | R49: 101 | S49: 025_02 和尚肾精不足（银钱+2000）

Sheet 普通
A1: 年份 | B1: 节气 | C1: 妙手回春次数 | D1: 李言闻收入 | E1: 诊费预期 | F1: 药材净收入预期 | G1: 谢仪预期 | H1: 田租 | I1: 剧情银钱奖励 | J1: 预期收入 | K1: 累计预期收入 | L1: 预期支出 | M1: 累计预期支出 | N1: 本节气收支差 | O1: 累计收支差 | P1: 含初始资金余额 | Q1: 节气末名望 | R1: 节气末心得 | S1: 剧情备注
A2: 1 | B2: 立春 | C2: 0 | D2: 0 | E2: 0 | F2: =IF(C2>=1,VLOOKUP(0+MAX(0,R2-0-C2)+0,药材收益口径!$H$2:$I$222,2,FALSE),0)+IF(C2>=2,VLOOKUP(0+MAX(0,R2-0-C2)+1,药材收益口径!$H$2:$I$222,2,FALSE),0)+IF(C2>=3,VLOOKUP(0+MAX(0,R2-0-C2)+2,药材收益口径!$H$2:$I$222,2,FALSE),0)+IF(C2>=4,VLOOKUP(0+MAX(0,R2-0-C2)+3,药材收益口径!$H$2:$I$222,2,FALSE),0) -> 0 | G2: 0 | H2: 0 | I2: 0 | J2: =SUM(D2:I2) -> 0 | K2: =J2 -> 0 | L2: =K2 -> 0 | M2: =L2 -> 0 | N2: =J2-L2 -> 0 | O2: =K2-M2 -> 0 | P2: =20000+O2 -> 20000 | Q2: 0 | R2: 0
A3: 1 | B3: 雨水 | C3: 3 | D3: 500 | E3: 60 | F3: =IF(C3>=1,VLOOKUP(R2+MAX(0,R3-R2-C3)+0,药材收益口径!$H$2:$I$222,2,FALSE),0)+IF(C3>=2,VLOOKUP(R2+MAX(0,R3-R2-C3)+1,药材收益口径!$H$2:$I$222,2,FALSE),0)+IF(C3>=3,VLOOKUP(R2+MAX(0,R3-R2-C3)+2,药材收益口径!$H$2:$I$222,2,FALSE),0)+IF(C3>=4,VLOOKUP(R2+MAX(0,R3-R2-C3)+3,药材收益口径!$H$2:$I$222,2,FALSE),0) -> 59 | G3: 345.6 | H3: 0 | I3: 0 | J3: =SUM(D3:I3) -> 964.6 | K3: =K2+J3 -> 964.6 | L3: 2776.4 | M3: =M2+L3 -> 2776.4 | N3: =J3-L3 -> -1811.8 | O3: =K3-M3 -> -1811.8 | P3: =20000+O3 -> 18188.2 | Q3: 30 | R3: 3
A4: 1 | B4: 惊蛰 | C4: 3 | D4: 500 | E4: 60 | F4: =IF(C4>=1,VLOOKUP(R3+MAX(0,R4-R3-C4)+0,药材收益口径!$H$2:$I$222,2,FALSE),0)+IF(C4>=2,VLOOKUP(R3+MAX(0,R4-R3-C4)+1,药材收益口径!$H$2:$I$222,2,FALSE),0)+IF(C4>=3,VLOOKUP(R3+MAX(0,R4-R3-C4)+2,药材收益口径!$H$2:$I$222,2,FALSE),0)+IF(C4>=4,VLOOKUP(R3+MAX(0,R4-R3-C4)+3,药材收益口径!$H$2:$I$222,2,FALSE),0) -> 59 | G4: 345.6 | H4: 0 | I4: 0 | J4: =SUM(D4:I4) -> 964.6 | K4: =K3+J4 -> 1929.2 | L4: 1550 | M4: =M3+L4 -> 4326.4 | N4: =J4-L4 -> -585.4 | O4: =K4-M4 -> -2397.2 | P4: =20000+O4 -> 17602.8 | Q4: 60 | R4: 6
A5: 1 | B5: 春分 | C5: 3 | D5: 500 | E5: 60 | F5: =IF(C5>=1,VLOOKUP(R4+MAX(0,R5-R4-C5)+0,药材收益口径!$H$2:$I$222,2,FALSE),0)+IF(C5>=2,VLOOKUP(R4+MAX(0,R5-R4-C5)+1,药材收益口径!$H$2:$I$222,2,FALSE),0)+IF(C5>=3,VLOOKUP(R4+MAX(0,R5-R4-C5)+2,药材收益口径!$H$2:$I$222,2,FALSE),0)+IF(C5>=4,VLOOKUP(R4+MAX(0,R5-R4-C5)+3,药材收益口径!$H$2:$I$222,2,FALSE),0) -> 59 | G5: 345.6 | H5: 0 | I5: 0 | J5: =SUM(D5:I5) -> 964.6 | K5: =K4+J5 -> 2893.8 | L5: 3376.4 | M5: =M4+L5 -> 7702.8 | N5: =J5-L5 -> -2411.8 | O5: =K5-M5 -> -4809 | P5: =20000+O5 -> 15191 | Q5: 90 | R5: 9
A6: 1 | B6: 清明 | C6: 3 | D6: 500 | E6: 90 | F6: =IF(C6>=1,VLOOKUP(R5+MAX(0,R6-R5-C6)+0,药材收益口径!$H$2:$I$222,2,FALSE),0)+IF(C6>=2,VLOOKUP(R5+MAX(0,R6-R5-C6)+1,药材收益口径!$H$2:$I$222,2,FALSE),0)+IF(C6>=3,VLOOKUP(R5+MAX(0,R6-R5-C6)+2,药材收益口径!$H$2:$I$222,2,FALSE),0)+IF(C6>=4,VLOOKUP(R5+MAX(0,R6-R5-C6)+3,药材收益口径!$H$2:$I$222,2,FALSE),0) -> 207.75 | G6: 345.6 | H6: 0 | I6: 0 | J6: =SUM(D6:I6) -> 1143.35 | K6: =K5+J6 -> 4037.15 | L6: 3550 | M6: =M5+L6 -> 11252.8 | N6: =J6-L6 -> -2406.65 | O6: =K6-M6 -> -7215.65 | P6: =20000+O6 -> 12784.35 | Q6: 120 | R6: 12
A7: 1 | B7: 谷雨 | C7: 3 | D7: 500 | E7: 150 | F7: =IF(C7>=1,VLOOKUP(R6+MAX(0,R7-R6-C7)+0,药材收益口径!$H$2:$I$222,2,FALSE),0)+IF(C7>=2,VLOOKUP(R6+MAX(0,R7-R6-C7)+1,药材收益口径!$H$2:$I$222,2,FALSE),0)+IF(C7>=3,VLOOKUP(R6+MAX(0,R7-R6-C7)+2,药材收益口径!$H$2:$I$222,2,FALSE),0)+IF(C7>=4,VLOOKUP(R6+MAX(0,R7-R6-C7)+3,药材收益口径!$H$2:$I$222,2,FALSE),0) -> 199.8 | G7: 345.6 | H7: 0 | I7: 0 | J7: =SUM(D7:I7) -> 1195.4 | K7: =K6+J7 -> 5232.55 | L7: 2776.4 | M7: =M6+L7 -> 14029.2 | N7: =J7-L7 -> -1581 | O7: =K7-M7 -> -8796.65 | P7: =20000+O7 -> 11203.35 | Q7: 150 | R7: 15
A8: 1 | B8: 立夏 | C8: 3 | D8: 500 | E8: 150 | F8: =IF(C8>=1,VLOOKUP(R7+MAX(0,R8-R7-C8)+0,药材收益口径!$H$2:$I$222,2,FALSE),0)+IF(C8>=2,VLOOKUP(R7+MAX(0,R8-R7-C8)+1,药材收益口径!$H$2:$I$222,2,FALSE),0)+IF(C8>=3,VLOOKUP(R7+MAX(0,R8-R7-C8)+2,药材收益口径!$H$2:$I$222,2,FALSE),0)+IF(C8>=4,VLOOKUP(R7+MAX(0,R8-R7-C8)+3,药材收益口径!$H$2:$I$222,2,FALSE),0) -> 183.9 | G8: 345.6 | H8: 0 | I8: 1000 | J8: =SUM(D8:I8) -> 2179.5 | K8: =K7+J8 -> 7412.05 | L8: 2650 | M8: =M7+L8 -> 16679.2 | N8: =J8-L8 -> -470.5 | O8: =K8-M8 -> -9267.15 | P8: =20000+O8 -> 10732.85 | Q8: 180 | R8: 18 | S8: 022_02 敬亭治疗成功（银钱+1000）
A9: 1 | B9: 小满 | C9: 3 | D9: 500 | E9: 150 | F9: =IF(C9>=1,VLOOKUP(R8+MAX(0,R9-R8-C9)+0,药材收益口径!$H$2:$I$222,2,FALSE),0)+IF(C9>=2,VLOOKUP(R8+MAX(0,R9-R8-C9)+1,药材收益口径!$H$2:$I$222,2,FALSE),0)+IF(C9>=3,VLOOKUP(R8+MAX(0,R9-R8-C9)+2,药材收益口径!$H$2:$I$222,2,FALSE),0)+IF(C9>=4,VLOOKUP(R8+MAX(0,R9-R8-C9)+3,药材收益口径!$H$2:$I$222,2,FALSE),0) -> 178.88333 | G9: 345.6 | H9: 0 | I9: 0 | J9: =SUM(D9:I9) -> 1174.4833 | K9: =K8+J9 -> 8586.5333 | L9: 3676.4 | M9: =M8+L9 -> 20355.6 | N9: =J9-L9 -> -2501.9167 | O9: =K9-M9 -> -11769.067 | P9: =20000+O9 -> 8230.9333 | Q9: 210 | R9: 21
A10: 1 | B10: 芒种 | C10: 3 | D10: 500 | E10: 150 | F10: =IF(C10>=1,VLOOKUP(R9+MAX(0,R10-R9-C10)+0,药材收益口径!$H$2:$I$222,2,FALSE),0)+IF(C10>=2,VLOOKUP(R9+MAX(0,R10-R9-C10)+1,药材收益口径!$H$2:$I$222,2,FALSE),0)+IF(C10>=3,VLOOKUP(R9+MAX(0,R10-R9-C10)+2,药材收益口径!$H$2:$I$222,2,FALSE),0)+IF(C10>=4,VLOOKUP(R9+MAX(0,R10-R9-C10)+3,药材收益口径!$H$2:$I$222,2,FALSE),0) -> 183.5625 | G10: 345.6 | H10: 0 | I10: 0 | J10: =SUM(D10:I10) -> 1179.1625 | K10: =K9+J10 -> 9765.6958 | L10: 2450 | M10: =M9+L10 -> 22805.6 | N10: =J10-L10 -> -1270.8375 | O10: =K10-M10 -> -13039.904 | P10: =20000+O10 -> 6960.0958 | Q10: 240 | R10: 24
A11: 1 | B11: 夏至 | C11: 3 | D11: 500 | E11: 150 | F11: =IF(C11>=1,VLOOKUP(R10+MAX(0,R11-R10-C11)+0,药材收益口径!$H$2:$I$222,2,FALSE),0)+IF(C11>=2,VLOOKUP(R10+MAX(0,R11-R10-C11)+1,药材收益口径!$H$2:$I$222,2,FALSE),0)+IF(C11>=3,VLOOKUP(R10+MAX(0,R11-R10-C11)+2,药材收益口径!$H$2:$I$222,2,FALSE),0)+IF(C11>=4,VLOOKUP(R10+MAX(0,R11-R10-C11)+3,药材收益口径!$H$2:$I$222,2,FALSE),0) -> 315.5322 | G11: 345.6 | H11: 0 | I11: 0 | J11: =SUM(D11:I11) -> 1311.1322 | K11: =K10+J11 -> 11076.828 | L11: 3676.4 | M11: =M10+L11 -> 26482 | N11: =J11-L11 -> -2365.2678 | O11: =K11-M11 -> -15405.172 | P11: =20000+O11 -> 4594.828 | Q11: 270 | R11: 27
A12: 1 | B12: 小暑 | C12: 3 | D12: 500 | E12: 150 | F12: =IF(C12>=1,VLOOKUP(R11+MAX(0,R12-R11-C12)+0,药材收益口径!$H$2:$I$222,2,FALSE),0)+IF(C12>=2,VLOOKUP(R11+MAX(0,R12-R11-C12)+1,药材收益口径!$H$2:$I$222,2,FALSE),0)+IF(C12>=3,VLOOKUP(R11+MAX(0,R12-R11-C12)+2,药材收益口径!$H$2:$I$222,2,FALSE),0)+IF(C12>=4,VLOOKUP(R11+MAX(0,R12-R11-C12)+3,药材收益口径!$H$2:$I$222,2,FALSE),0) -> 332.5979 | G12: 345.6 | H12: 0 | I12: 0 | J12: =SUM(D12:I12) -> 1328.1979 | K12: =K11+J12 -> 12405.026 | L12: 2450 | M12: =M11+L12 -> 28932 | N12: =J12-L12 -> -1121.8021 | O12: =K12-M12 -> -16526.974 | P12: =20000+O12 -> 3473.0259 | Q12: 300 | R12: 30
A13: 1 | B13: 大暑 | C13: 3 | D13: 500 | E13: 450 | F13: =IF(C13>=1,VLOOKUP(R12+MAX(0,R13-R12-C13)+0,药材收益口径!$H$2:$I$222,2,FALSE),0)+IF(C13>=2,VLOOKUP(R12+MAX(0,R13-R12-C13)+1,药材收益口径!$H$2:$I$222,2,FALSE),0)+IF(C13>=3,VLOOKUP(R12+MAX(0,R13-R12-C13)+2,药材收益口径!$H$2:$I$222,2,FALSE),0)+IF(C13>=4,VLOOKUP(R12+MAX(0,R13-R12-C13)+3,药材收益口径!$H$2:$I$222,2,FALSE),0) -> 323.19231 | G13: 345.6 | H13: 5000 | I13: 0 | J13: =SUM(D13:I13) -> 6618.7923 | K13: =K12+J13 -> 19023.818 | L13: 3276.4 | M13: =M12+L13 -> 32208.4 | N13: =J13-L13 -> 3342.3923 | O13: =K13-M13 -> -13184.582 | P13: =20000+O13 -> 6815.4182 | Q13: 330 | R13: 33
A14: 1 | B14: 立秋 | C14: 3 | D14: 500 | E14: 600 | F14: =IF(C14>=1,VLOOKUP(R13+MAX(0,R14-R13-C14)+0,药材收益口径!$H$2:$I$222,2,FALSE),0)+IF(C14>=2,VLOOKUP(R13+MAX(0,R14-R13-C14)+1,药材收益口径!$H$2:$I$222,2,FALSE),0)+IF(C14>=3,VLOOKUP(R13+MAX(0,R14-R13-C14)+2,药材收益口径!$H$2:$I$222,2,FALSE),0)+IF(C14>=4,VLOOKUP(R13+MAX(0,R14-R13-C14)+3,药材收益口径!$H$2:$I$222,2,FALSE),0) -> 316.6 | G14: 345.6 | H14: 0 | I14: 0 | J14: =SUM(D14:I14) -> 1762.2 | K14: =K13+J14 -> 20786.018 | L14: 2650 | M14: =M13+L14 -> 34858.4 | N14: =J14-L14 -> -887.8 | O14: =K14-M14 -> -14072.382 | P14: =20000+O14 -> 5927.6182 | Q14: 360 | R14: 36
A15: 1 | B15: 处暑 | C15: 3 | D15: 500 | E15: 600 | F15: =IF(C15>=1,VLOOKUP(R14+MAX(0,R15-R14-C15)+0,药材收益口径!$H$2:$I$222,2,FALSE),0)+IF(C15>=2,VLOOKUP(R14+MAX(0,R15-R14-C15)+1,药材收益口径!$H$2:$I$222,2,FALSE),0)+IF(C15>=3,VLOOKUP(R14+MAX(0,R15-R14-C15)+2,药材收益口径!$H$2:$I$222,2,FALSE),0)+IF(C15>=4,VLOOKUP(R14+MAX(0,R15-R14-C15)+3,药材收益口径!$H$2:$I$222,2,FALSE),0) -> 313.90625 | G15: 345.6 | H15: 0 | I15: 0 | J15: =SUM(D15:I15) -> 1759.5062 | K15: =K14+J15 -> 22545.524 | L15: 4776.4 | M15: =M14+L15 -> 39634.8 | N15: =J15-L15 -> -3016.8937 | O15: =K15-M15 -> -17089.276 | P15: =20000+O15 -> 2910.7245 | Q15: 390 | R15: 39
A16: 1 | B16: 白露 | C16: 3 | D16: 500 | E16: 600 | F16: =IF(C16>=1,VLOOKUP(R15+MAX(0,R16-R15-C16)+0,药材收益口径!$H$2:$I$222,2,FALSE),0)+IF(C16>=2,VLOOKUP(R15+MAX(0,R16-R15-C16)+1,药材收益口径!$H$2:$I$222,2,FALSE),0)+IF(C16>=3,VLOOKUP(R15+MAX(0,R16-R15-C16)+2,药材收益口径!$H$2:$I$222,2,FALSE),0)+IF(C16>=4,VLOOKUP(R15+MAX(0,R16-R15-C16)+3,药材收益口径!$H$2:$I$222,2,FALSE),0) -> 318.44444 | G16: 345.6 | H16: 0 | I16: 0 | J16: =SUM(D16:I16) -> 1764.0444 | K16: =K15+J16 -> 24309.569 | L16: 1550 | M16: =M15+L16 -> 41184.8 | N16: =J16-L16 -> 214.04444 | O16: =K16-M16 -> -16875.231 | P16: =20000+O16 -> 3124.7689 | Q16: 420 | R16: 42
A17: 1 | B17: 秋分 | C17: 3 | D17: 500 | E17: 600 | F17: =IF(C17>=1,VLOOKUP(R16+MAX(0,R17-R16-C17)+0,药材收益口径!$H$2:$I$222,2,FALSE),0)+IF(C17>=2,VLOOKUP(R16+MAX(0,R17-R16-C17)+1,药材收益口径!$H$2:$I$222,2,FALSE),0)+IF(C17>=3,VLOOKUP(R16+MAX(0,R17-R16-C17)+2,药材收益口径!$H$2:$I$222,2,FALSE),0)+IF(C17>=4,VLOOKUP(R16+MAX(0,R17-R16-C17)+3,药材收益口径!$H$2:$I$222,2,FALSE),0) -> 319.91813 | G17: 345.6 | H17: 0 | I17: 1000 | J17: =SUM(D17:I17) -> 2765.5181 | K17: =K16+J17 -> 27075.087 | L17: 3376.4 | M17: =M16+L17 -> 44561.2 | N17: =J17-L17 -> -610.88187 | O17: =K17-M17 -> -17486.113 | P17: =20000+O17 -> 2513.8871 | Q17: 450 | R17: 45 | S17: 023_02 谢飞燕肺气虚（银钱+1000）
A18: 1 | B18: 寒露 | C18: 3 | D18: 500 | E18: 600 | F18: =IF(C18>=1,VLOOKUP(R17+MAX(0,R18-R17-C18)+0,药材收益口径!$H$2:$I$222,2,FALSE),0)+IF(C18>=2,VLOOKUP(R17+MAX(0,R18-R17-C18)+1,药材收益口径!$H$2:$I$222,2,FALSE),0)+IF(C18>=3,VLOOKUP(R17+MAX(0,R18-R17-C18)+2,药材收益口径!$H$2:$I$222,2,FALSE),0)+IF(C18>=4,VLOOKUP(R17+MAX(0,R18-R17-C18)+3,药材收益口径!$H$2:$I$222,2,FALSE),0) -> 314.92105 | G18: 345.6 | H18: 0 | I18: 1000 | J18: =SUM(D18:I18) -> 2760.5211 | K18: =K17+J18 -> 29835.608 | L18: 1550 | M18: =M17+L18 -> 46111.2 | N18: =J18-L18 -> 1210.5211 | O18: =K18-M18 -> -16275.592 | P18: =20000+O18 -> 3724.4081 | Q18: 480 | R18: 48 | S18: 024_02 谢飞燕肺阴虚（银钱+1000）
A19: 1 | B19: 霜降 | C19: 3 | D19: 500 | E19: 600 | F19: =IF(C19>=1,VLOOKUP(R18+MAX(0,R19-R18-C19)+0,药材收益口径!$H$2:$I$222,2,FALSE),0)+IF(C19>=2,VLOOKUP(R18+MAX(0,R19-R18-C19)+1,药材收益口径!$H$2:$I$222,2,FALSE),0)+IF(C19>=3,VLOOKUP(R18+MAX(0,R19-R18-C19)+2,药材收益口径!$H$2:$I$222,2,FALSE),0)+IF(C19>=4,VLOOKUP(R18+MAX(0,R19-R18-C19)+3,药材收益口径!$H$2:$I$222,2,FALSE),0) -> 364.29535 | G19: 345.6 | H19: 15000 | I19: 0 | J19: =SUM(D19:I19) -> 16809.895 | K19: =K18+J19 -> 46645.503 | L19: 4276.4 | M19: =M18+L19 -> 50387.6 | N19: =J19-L19 -> 12533.495 | O19: =K19-M19 -> -3742.0965 | P19: =20000+O19 -> 16257.903 | Q19: 510 | R19: 51
A20: 1 | B20: 立冬 | C20: 3 | D20: 500 | E20: 600 | F20: =IF(C20>=1,VLOOKUP(R19+MAX(0,R20-R19-C20)+0,药材收益口径!$H$2:$I$222,2,FALSE),0)+IF(C20>=2,VLOOKUP(R19+MAX(0,R20-R19-C20)+1,药材收益口径!$H$2:$I$222,2,FALSE),0)+IF(C20>=3,VLOOKUP(R19+MAX(0,R20-R19-C20)+2,药材收益口径!$H$2:$I$222,2,FALSE),0)+IF(C20>=4,VLOOKUP(R19+MAX(0,R20-R19-C20)+3,药材收益口径!$H$2:$I$222,2,FALSE),0) -> 354.97925 | G20: 345.6 | H20: 0 | I20: 0 | J20: =SUM(D20:I20) -> 1800.5792 | K20: =K19+J20 -> 48446.083 | L20: 4750 | M20: =M19+L20 -> 55137.6 | N20: =J20-L20 -> -2949.4208 | O20: =K20-M20 -> -6691.5173 | P20: =20000+O20 -> 13308.483 | Q20: 540 | R20: 54
A21: 1 | B21: 小雪 | C21: 3 | D21: 500 | E21: 600 | F21: =IF(C21>=1,VLOOKUP(R20+MAX(0,R21-R20-C21)+0,药材收益口径!$H$2:$I$222,2,FALSE),0)+IF(C21>=2,VLOOKUP(R20+MAX(0,R21-R20-C21)+1,药材收益口径!$H$2:$I$222,2,FALSE),0)+IF(C21>=3,VLOOKUP(R20+MAX(0,R21-R20-C21)+2,药材收益口径!$H$2:$I$222,2,FALSE),0)+IF(C21>=4,VLOOKUP(R20+MAX(0,R21-R20-C21)+3,药材收益口径!$H$2:$I$222,2,FALSE),0) -> 352.74471 | G21: 345.6 | H21: 0 | I21: 1000 | J21: =SUM(D21:I21) -> 2798.3447 | K21: =K20+J21 -> 51244.427 | L21: 2776.4 | M21: =M20+L21 -> 57914 | N21: =J21-L21 -> 21.944709 | O21: =K21-M21 -> -6669.5726 | P21: =20000+O21 -> 13330.427 | Q21: 1570 | R21: 64 | S21: 024_04 王百堂来访（心得+7）；005_02 治愈世子（银钱+1000，名望+1000）
A22: 1 | B22: 大雪 | C22: 3 | D22: 500 | E22: 1500 | F22: =IF(C22>=1,VLOOKUP(R21+MAX(0,R22-R21-C22)+0,药材收益口径!$H$2:$I$222,2,FALSE),0)+IF(C22>=2,VLOOKUP(R21+MAX(0,R22-R21-C22)+1,药材收益口径!$H$2:$I$222,2,FALSE),0)+IF(C22>=3,VLOOKUP(R21+MAX(0,R22-R21-C22)+2,药材收益口径!$H$2:$I$222,2,FALSE),0)+IF(C22>=4,VLOOKUP(R21+MAX(0,R22-R21-C22)+3,药材收益口径!$H$2:$I$222,2,FALSE),0) -> 351.58929 | G22: 345.6 | H22: 0 | I22: 0 | J22: =SUM(D22:I22) -> 2697.1893 | K22: =K21+J22 -> 53941.617 | L22: 1550 | M22: =M21+L22 -> 59464 | N22: =J22-L22 -> 1147.1893 | O22: =K22-M22 -> -5522.3833 | P22: =20000+O22 -> 14477.617 | Q22: 1600 | R22: 67
A23: 1 | B23: 冬至 | C23: 3 | D23: 500 | E23: 1500 | F23: =IF(C23>=1,VLOOKUP(R22+MAX(0,R23-R22-C23)+0,药材收益口径!$H$2:$I$222,2,FALSE),0)+IF(C23>=2,VLOOKUP(R22+MAX(0,R23-R22-C23)+1,药材收益口径!$H$2:$I$222,2,FALSE),0)+IF(C23>=3,VLOOKUP(R22+MAX(0,R23-R22-C23)+2,药材收益口径!$H$2:$I$222,2,FALSE),0)+IF(C23>=4,VLOOKUP(R22+MAX(0,R23-R22-C23)+3,药材收益口径!$H$2:$I$222,2,FALSE),0) -> 372.87931 | G23: 345.6 | H23: 0 | I23: 0 | J23: =SUM(D23:I23) -> 2718.4793 | K23: =K22+J23 -> 56660.096 | L23: 2776.4 | M23: =M22+L23 -> 62240.4 | N23: =J23-L23 -> -57.92069 | O23: =K23-M23 -> -5580.304 | P23: =20000+O23 -> 14419.696 | Q23: 1630 | R23: 70
A24: 1 | B24: 小寒 | C24: 3 | D24: 500 | E24: 1500 | F24: =IF(C24>=1,VLOOKUP(R23+MAX(0,R24-R23-C24)+0,药材收益口径!$H$2:$I$222,2,FALSE),0)+IF(C24>=2,VLOOKUP(R23+MAX(0,R24-R23-C24)+1,药材收益口径!$H$2:$I$222,2,FALSE),0)+IF(C24>=3,VLOOKUP(R23+MAX(0,R24-R23-C24)+2,药材收益口径!$H$2:$I$222,2,FALSE),0)+IF(C24>=4,VLOOKUP(R23+MAX(0,R24-R23-C24)+3,药材收益口径!$H$2:$I$222,2,FALSE),0) -> 370.73137 | G24: 345.6 | H24: 0 | I24: 0 | J24: =SUM(D24:I24) -> 2716.3314 | K24: =K23+J24 -> 59376.427 | L24: 1550 | M24: =M23+L24 -> 63790.4 | N24: =J24-L24 -> 1166.3314 | O24: =K24-M24 -> -4413.9726 | P24: =20000+O24 -> 15586.027 | Q24: 1660 | R24: 73
A25: 1 | B25: 大寒 | C25: 3 | D25: 500 | E25: 1500 | F25: =IF(C25>=1,VLOOKUP(R24+MAX(0,R25-R24-C25)+0,药材收益口径!$H$2:$I$222,2,FALSE),0)+IF(C25>=2,VLOOKUP(R24+MAX(0,R25-R24-C25)+1,药材收益口径!$H$2:$I$222,2,FALSE),0)+IF(C25>=3,VLOOKUP(R24+MAX(0,R25-R24-C25)+2,药材收益口径!$H$2:$I$222,2,FALSE),0)+IF(C25>=4,VLOOKUP(R24+MAX(0,R25-R24-C25)+3,药材收益口径!$H$2:$I$222,2,FALSE),0) -> 387.93095 | G25: 345.6 | H25: 0 | I25: 0 | J25: =SUM(D25:I25) -> 2733.5309 | K25: =K24+J25 -> 62109.958 | L25: 3376.4 | M25: =M24+L25 -> 67166.8 | N25: =J25-L25 -> -642.86905 | O25: =K25-M25 -> -5056.8417 | P25: =20000+O25 -> 14943.158 | Q25: 1690 | R25: 76
A26: 2 | B26: 立春 | C26: 3 | D26: 500 | E26: 1500 | F26: =IF(C26>=1,VLOOKUP(R25+MAX(0,R26-R25-C26)+0,药材收益口径!$H$2:$I$222,2,FALSE),0)+IF(C26>=2,VLOOKUP(R25+MAX(0,R26-R25-C26)+1,药材收益口径!$H$2:$I$222,2,FALSE),0)+IF(C26>=3,VLOOKUP(R25+MAX(0,R26-R25-C26)+2,药材收益口径!$H$2:$I$222,2,FALSE),0)+IF(C26>=4,VLOOKUP(R25+MAX(0,R26-R25-C26)+3,药材收益口径!$H$2:$I$222,2,FALSE),0) -> 433.35339 | G26: 345.6 | H26: 0 | I26: 0 | J26: =SUM(D26:I26) -> 2778.9534 | K26: =K25+J26 -> 64888.912 | L26: 2650 | M26: =M25+L26 -> 69816.8 | N26: =J26-L26 -> 128.95339 | O26: =K26-M26 -> -4927.8883 | P26: =20000+O26 -> 15072.112 | Q26: 1720 | R26: 79
A27: 2 | B27: 雨水 | C27: 3 | D27: 500 | E27: 1500 | F27: =IF(C27>=1,VLOOKUP(R26+MAX(0,R27-R26-C27)+0,药材收益口径!$H$2:$I$222,2,FALSE),0)+IF(C27>=2,VLOOKUP(R26+MAX(0,R27-R26-C27)+1,药材收益口径!$H$2:$I$222,2,FALSE),0)+IF(C27>=3,VLOOKUP(R26+MAX(0,R27-R26-C27)+2,药材收益口径!$H$2:$I$222,2,FALSE),0)+IF(C27>=4,VLOOKUP(R26+MAX(0,R27-R26-C27)+3,药材收益口径!$H$2:$I$222,2,FALSE),0) -> 446.26218 | G27: 345.6 | H27: 0 | I27: 0 | J27: =SUM(D27:I27) -> 2791.8622 | K27: =K26+J27 -> 67680.774 | L27: 2776.4 | M27: =M26+L27 -> 72593.2 | N27: =J27-L27 -> 15.462185 | O27: =K27-M27 -> -4912.4261 | P27: =20000+O27 -> 15087.574 | Q27: 1750 | R27: 82
A28: 2 | B28: 惊蛰 | C28: 3 | D28: 500 | E28: 1500 | F28: =IF(C28>=1,VLOOKUP(R27+MAX(0,R28-R27-C28)+0,药材收益口径!$H$2:$I$222,2,FALSE),0)+IF(C28>=2,VLOOKUP(R27+MAX(0,R28-R27-C28)+1,药材收益口径!$H$2:$I$222,2,FALSE),0)+IF(C28>=3,VLOOKUP(R27+MAX(0,R28-R27-C28)+2,药材收益口径!$H$2:$I$222,2,FALSE),0)+IF(C28>=4,VLOOKUP(R27+MAX(0,R28-R27-C28)+3,药材收益口径!$H$2:$I$222,2,FALSE),0) -> 445.75714 | G28: 345.6 | H28: 0 | I28: 0 | J28: =SUM(D28:I28) -> 2791.3571 | K28: =K27+J28 -> 70472.131 | L28: 1550 | M28: =M27+L28 -> 74143.2 | N28: =J28-L28 -> 1241.3571 | O28: =K28-M28 -> -3671.069 | P28: =20000+O28 -> 16328.931 | Q28: 1780 | R28: 85
A29: 2 | B29: 春分 | C29: 3 | D29: 500 | E29: 1500 | F29: =IF(C29>=1,VLOOKUP(R28+MAX(0,R29-R28-C29)+0,药材收益口径!$H$2:$I$222,2,FALSE),0)+IF(C29>=2,VLOOKUP(R28+MAX(0,R29-R28-C29)+1,药材收益口径!$H$2:$I$222,2,FALSE),0)+IF(C29>=3,VLOOKUP(R28+MAX(0,R29-R28-C29)+2,药材收益口径!$H$2:$I$222,2,FALSE),0)+IF(C29>=4,VLOOKUP(R28+MAX(0,R29-R28-C29)+3,药材收益口径!$H$2:$I$222,2,FALSE),0) -> 434.38551 | G29: 345.6 | H29: 0 | I29: 0 | J29: =SUM(D29:I29) -> 2779.9855 | K29: =K28+J29 -> 73252.117 | L29: 3376.4 | M29: =M28+L29 -> 77519.6 | N29: =J29-L29 -> -596.41449 | O29: =K29-M29 -> -4267.4834 | P29: =20000+O29 -> 15732.517 | Q29: 1810 | R29: 88
A30: 2 | B30: 清明 | C30: 3 | D30: 500 | E30: 1500 | F30: =IF(C30>=1,VLOOKUP(R29+MAX(0,R30-R29-C30)+0,药材收益口径!$H$2:$I$222,2,FALSE),0)+IF(C30>=2,VLOOKUP(R29+MAX(0,R30-R29-C30)+1,药材收益口径!$H$2:$I$222,2,FALSE),0)+IF(C30>=3,VLOOKUP(R29+MAX(0,R30-R29-C30)+2,药材收益口径!$H$2:$I$222,2,FALSE),0)+IF(C30>=4,VLOOKUP(R29+MAX(0,R30-R29-C30)+3,药材收益口径!$H$2:$I$222,2,FALSE),0) -> 429.59354 | G30: 345.6 | H30: 0 | I30: 0 | J30: =SUM(D30:I30) -> 2775.1935 | K30: =K29+J30 -> 76027.31 | L30: 3550 | M30: =M29+L30 -> 81069.6 | N30: =J30-L30 -> -774.80646 | O30: =K30-M30 -> -5042.2899 | P30: =20000+O30 -> 14957.71 | Q30: 1840 | R30: 91
A31: 2 | B31: 谷雨 | C31: 3 | D31: 500 | E31: 1500 | F31: =IF(C31>=1,VLOOKUP(R30+MAX(0,R31-R30-C31)+0,药材收益口径!$H$2:$I$222,2,FALSE),0)+IF(C31>=2,VLOOKUP(R30+MAX(0,R31-R30-C31)+1,药材收益口径!$H$2:$I$222,2,FALSE),0)+IF(C31>=3,VLOOKUP(R30+MAX(0,R31-R30-C31)+2,药材收益口径!$H$2:$I$222,2,FALSE),0)+IF(C31>=4,VLOOKUP(R30+MAX(0,R31-R30-C31)+3,药材收益口径!$H$2:$I$222,2,FALSE),0) -> 433.33354 | G31: 345.6 | H31: 0 | I31: 0 | J31: =SUM(D31:I31) -> 2778.9335 | K31: =K30+J31 -> 78806.244 | L31: 2776.4 | M31: =M30+L31 -> 83846 | N31: =J31-L31 -> 2.5335444 | O31: =K31-M31 -> -5039.7564 | P31: =20000+O31 -> 14960.244 | Q31: 1870 | R31: 94
A32: 2 | B32: 立夏 | C32: 3 | D32: 500 | E32: 1500 | F32: =IF(C32>=1,VLOOKUP(R31+MAX(0,R32-R31-C32)+0,药材收益口径!$H$2:$I$222,2,FALSE),0)+IF(C32>=2,VLOOKUP(R31+MAX(0,R32-R31-C32)+1,药材收益口径!$H$2:$I$222,2,FALSE),0)+IF(C32>=3,VLOOKUP(R31+MAX(0,R32-R31-C32)+2,药材收益口径!$H$2:$I$222,2,FALSE),0)+IF(C32>=4,VLOOKUP(R31+MAX(0,R32-R31-C32)+3,药材收益口径!$H$2:$I$222,2,FALSE),0) -> 432.48918 | G32: 345.6 | H32: 0 | I32: 0 | J32: =SUM(D32:I32) -> 2778.0892 | K32: =K31+J32 -> 81584.333 | L32: 2650 | M32: =M31+L32 -> 86496 | N32: =J32-L32 -> 128.08918 | O32: =K32-M32 -> -4911.6672 | P32: =20000+O32 -> 15088.333 | Q32: 1900 | R32: 97
A33: 2 | B33: 小满 | C33: 3 | D33: 500 | E33: 1500 | F33: =IF(C33>=1,VLOOKUP(R32+MAX(0,R33-R32-C33)+0,药材收益口径!$H$2:$I$222,2,FALSE),0)+IF(C33>=2,VLOOKUP(R32+MAX(0,R33-R32-C33)+1,药材收益口径!$H$2:$I$222,2,FALSE),0)+IF(C33>=3,VLOOKUP(R32+MAX(0,R33-R32-C33)+2,药材收益口径!$H$2:$I$222,2,FALSE),0)+IF(C33>=4,VLOOKUP(R32+MAX(0,R33-R32-C33)+3,药材收益口径!$H$2:$I$222,2,FALSE),0) -> 439.12753 | G33: 345.6 | H33: 0 | I33: 0 | J33: =SUM(D33:I33) -> 2784.7275 | K33: =K32+J33 -> 84369.06 | L33: 3676.4 | M33: =M32+L33 -> 90172.4 | N33: =J33-L33 -> -891.67247 | O33: =K33-M33 -> -5803.3397 | P33: =20000+O33 -> 14196.66 | Q33: 1930 | R33: 100
A34: 2 | B34: 芒种 | C34: 3 | D34: 500 | E34: 1500 | F34: =IF(C34>=1,VLOOKUP(R33+MAX(0,R34-R33-C34)+0,药材收益口径!$H$2:$I$222,2,FALSE),0)+IF(C34>=2,VLOOKUP(R33+MAX(0,R34-R33-C34)+1,药材收益口径!$H$2:$I$222,2,FALSE),0)+IF(C34>=3,VLOOKUP(R33+MAX(0,R34-R33-C34)+2,药材收益口径!$H$2:$I$222,2,FALSE),0)+IF(C34>=4,VLOOKUP(R33+MAX(0,R34-R33-C34)+3,药材收益口径!$H$2:$I$222,2,FALSE),0) -> 443.83333 | G34: 345.6 | H34: 0 | I34: 2000 | J34: =SUM(D34:I34) -> 4789.4333 | K34: =K33+J34 -> 89158.494 | L34: 2450 | M34: =M33+L34 -> 92622.4 | N34: =J34-L34 -> 2339.4333 | O34: =K34-M34 -> -3463.9063 | P34: =20000+O34 -> 16536.094 | Q34: 1960 | R34: 103 | S34: 025_02 和尚肾精不足（银钱+2000）
A35: 2 | B35: 夏至 | C35: 3 | D35: 500 | E35: 1500 | F35: =IF(C35>=1,VLOOKUP(R34+MAX(0,R35-R34-C35)+0,药材收益口径!$H$2:$I$222,2,FALSE),0)+IF(C35>=2,VLOOKUP(R34+MAX(0,R35-R34-C35)+1,药材收益口径!$H$2:$I$222,2,FALSE),0)+IF(C35>=3,VLOOKUP(R34+MAX(0,R35-R34-C35)+2,药材收益口径!$H$2:$I$222,2,FALSE),0)+IF(C35>=4,VLOOKUP(R34+MAX(0,R35-R34-C35)+3,药材收益口径!$H$2:$I$222,2,FALSE),0) -> 449.63145 | G35: 345.6 | H35: 0 | I35: 0 | J35: =SUM(D35:I35) -> 2795.2315 | K35: =K34+J35 -> 91953.725 | L35: 3676.4 | M35: =M34+L35 -> 96298.8 | N35: =J35-L35 -> -881.16855 | O35: =K35-M35 -> -4345.0749 | P35: =20000+O35 -> 15654.925 | Q35: 1990 | R35: 106
A36: 2 | B36: 小暑 | C36: 3 | D36: 500 | E36: 2000 | F36: =IF(C36>=1,VLOOKUP(R35+MAX(0,R36-R35-C36)+0,药材收益口径!$H$2:$I$222,2,FALSE),0)+IF(C36>=2,VLOOKUP(R35+MAX(0,R36-R35-C36)+1,药材收益口径!$H$2:$I$222,2,FALSE),0)+IF(C36>=3,VLOOKUP(R35+MAX(0,R36-R35-C36)+2,药材收益口径!$H$2:$I$222,2,FALSE),0)+IF(C36>=4,VLOOKUP(R35+MAX(0,R36-R35-C36)+3,药材收益口径!$H$2:$I$222,2,FALSE),0) -> 447.82748 | G36: 345.6 | H36: 0 | I36: 0 | J36: =SUM(D36:I36) -> 3293.4275 | K36: =K35+J36 -> 95247.153 | L36: 2450 | M36: =M35+L36 -> 98748.8 | N36: =J36-L36 -> 843.42748 | O36: =K36-M36 -> -3501.6474 | P36: =20000+O36 -> 16498.353 | Q36: 2020 | R36: 109
A37: 2 | B37: 大暑 | C37: 3 | D37: 500 | E37: 3000 | F37: =IF(C37>=1,VLOOKUP(R36+MAX(0,R37-R36-C37)+0,药材收益口径!$H$2:$I$222,2,FALSE),0)+IF(C37>=2,VLOOKUP(R36+MAX(0,R37-R36-C37)+1,药材收益口径!$H$2:$I$222,2,FALSE),0)+IF(C37>=3,VLOOKUP(R36+MAX(0,R37-R36-C37)+2,药材收益口径!$H$2:$I$222,2,FALSE),0)+IF(C37>=4,VLOOKUP(R36+MAX(0,R37-R36-C37)+3,药材收益口径!$H$2:$I$222,2,FALSE),0) -> 447.45709 | G37: 345.6 | H37: 5000 | I37: 0 | J37: =SUM(D37:I37) -> 9293.0571 | K37: =K36+J37 -> 104540.21 | L37: 3276.4 | M37: =M36+L37 -> 102025.2 | N37: =J37-L37 -> 6016.6571 | O37: =K37-M37 -> 2515.0097 | P37: =20000+O37 -> 22515.01 | Q37: 2050 | R37: 112
A38: 2 | B38: 立秋 | C38: 3 | D38: 500 | E38: 3000 | F38: =IF(C38>=1,VLOOKUP(R37+MAX(0,R38-R37-C38)+0,药材收益口径!$H$2:$I$222,2,FALSE),0)+IF(C38>=2,VLOOKUP(R37+MAX(0,R38-R37-C38)+1,药材收益口径!$H$2:$I$222,2,FALSE),0)+IF(C38>=3,VLOOKUP(R37+MAX(0,R38-R37-C38)+2,药材收益口径!$H$2:$I$222,2,FALSE),0)+IF(C38>=4,VLOOKUP(R37+MAX(0,R38-R37-C38)+3,药材收益口径!$H$2:$I$222,2,FALSE),0) -> 447.45709 | G38: 345.6 | H38: 0 | I38: 0 | J38: =SUM(D38:I38) -> 4293.0571 | K38: =K37+J38 -> 108833.27 | L38: 2650 | M38: =M37+L38 -> 104675.2 | N38: =J38-L38 -> 1643.0571 | O38: =K38-M38 -> 4158.0668 | P38: =20000+O38 -> 24158.067 | Q38: 2080 | R38: 115
A39: 2 | B39: 处暑 | C39: 3 | D39: 500 | E39: 3000 | F39: =IF(C39>=1,VLOOKUP(R38+MAX(0,R39-R38-C39)+0,药材收益口径!$H$2:$I$222,2,FALSE),0)+IF(C39>=2,VLOOKUP(R38+MAX(0,R39-R38-C39)+1,药材收益口径!$H$2:$I$222,2,FALSE),0)+IF(C39>=3,VLOOKUP(R38+MAX(0,R39-R38-C39)+2,药材收益口径!$H$2:$I$222,2,FALSE),0)+IF(C39>=4,VLOOKUP(R38+MAX(0,R39-R38-C39)+3,药材收益口径!$H$2:$I$222,2,FALSE),0) -> 447.45709 | G39: 345.6 | H39: 0 | I39: 0 | J39: =SUM(D39:I39) -> 4293.0571 | K39: =K38+J39 -> 113126.32 | L39: 4776.4 | M39: =M38+L39 -> 109451.6 | N39: =J39-L39 -> -483.34291 | O39: =K39-M39 -> 3674.7239 | P39: =20000+O39 -> 23674.724 | Q39: 2110 | R39: 118
A40: 2 | B40: 白露 | C40: 3 | D40: 500 | E40: 3000 | F40: =IF(C40>=1,VLOOKUP(R39+MAX(0,R40-R39-C40)+0,药材收益口径!$H$2:$I$222,2,FALSE),0)+IF(C40>=2,VLOOKUP(R39+MAX(0,R40-R39-C40)+1,药材收益口径!$H$2:$I$222,2,FALSE),0)+IF(C40>=3,VLOOKUP(R39+MAX(0,R40-R39-C40)+2,药材收益口径!$H$2:$I$222,2,FALSE),0)+IF(C40>=4,VLOOKUP(R39+MAX(0,R40-R39-C40)+3,药材收益口径!$H$2:$I$222,2,FALSE),0) -> 447.45709 | G40: 345.6 | H40: 0 | I40: 0 | J40: =SUM(D40:I40) -> 4293.0571 | K40: =K39+J40 -> 117419.38 | L40: 1550 | M40: =M39+L40 -> 111001.6 | N40: =J40-L40 -> 2743.0571 | O40: =K40-M40 -> 6417.781 | P40: =20000+O40 -> 26417.781 | Q40: 2140 | R40: 121
A41: 2 | B41: 秋分 | C41: 3 | D41: 500 | E41: 3000 | F41: =IF(C41>=1,VLOOKUP(R40+MAX(0,R41-R40-C41)+0,药材收益口径!$H$2:$I$222,2,FALSE),0)+IF(C41>=2,VLOOKUP(R40+MAX(0,R41-R40-C41)+1,药材收益口径!$H$2:$I$222,2,FALSE),0)+IF(C41>=3,VLOOKUP(R40+MAX(0,R41-R40-C41)+2,药材收益口径!$H$2:$I$222,2,FALSE),0)+IF(C41>=4,VLOOKUP(R40+MAX(0,R41-R40-C41)+3,药材收益口径!$H$2:$I$222,2,FALSE),0) -> 447.45709 | G41: 345.6 | H41: 0 | I41: 0 | J41: =SUM(D41:I41) -> 4293.0571 | K41: =K40+J41 -> 121712.44 | L41: 3376.4 | M41: =M40+L41 -> 114378 | N41: =J41-L41 -> 916.65709 | O41: =K41-M41 -> 7334.4381 | P41: =20000+O41 -> 27334.438 | Q41: 2170 | R41: 124
A42: 2 | B42: 寒露 | C42: 3 | D42: 500 | E42: 3000 | F42: =IF(C42>=1,VLOOKUP(R41+MAX(0,R42-R41-C42)+0,药材收益口径!$H$2:$I$222,2,FALSE),0)+IF(C42>=2,VLOOKUP(R41+MAX(0,R42-R41-C42)+1,药材收益口径!$H$2:$I$222,2,FALSE),0)+IF(C42>=3,VLOOKUP(R41+MAX(0,R42-R41-C42)+2,药材收益口径!$H$2:$I$222,2,FALSE),0)+IF(C42>=4,VLOOKUP(R41+MAX(0,R42-R41-C42)+3,药材收益口径!$H$2:$I$222,2,FALSE),0) -> 447.45709 | G42: 345.6 | H42: 0 | I42: 0 | J42: =SUM(D42:I42) -> 4293.0571 | K42: =K41+J42 -> 126005.5 | L42: 1550 | M42: =M41+L42 -> 115928 | N42: =J42-L42 -> 2743.0571 | O42: =K42-M42 -> 10077.495 | P42: =20000+O42 -> 30077.495 | Q42: 2200 | R42: 127
A43: 2 | B43: 霜降 | C43: 3 | D43: 500 | E43: 3000 | F43: =IF(C43>=1,VLOOKUP(R42+MAX(0,R43-R42-C43)+0,药材收益口径!$H$2:$I$222,2,FALSE),0)+IF(C43>=2,VLOOKUP(R42+MAX(0,R43-R42-C43)+1,药材收益口径!$H$2:$I$222,2,FALSE),0)+IF(C43>=3,VLOOKUP(R42+MAX(0,R43-R42-C43)+2,药材收益口径!$H$2:$I$222,2,FALSE),0)+IF(C43>=4,VLOOKUP(R42+MAX(0,R43-R42-C43)+3,药材收益口径!$H$2:$I$222,2,FALSE),0) -> 447.45709 | G43: 345.6 | H43: 15000 | I43: 0 | J43: =SUM(D43:I43) -> 19293.057 | K43: =K42+J43 -> 145298.55 | L43: 4276.4 | M43: =M42+L43 -> 120204.4 | N43: =J43-L43 -> 15016.657 | O43: =K43-M43 -> 25094.152 | P43: =20000+O43 -> 45094.152 | Q43: 2230 | R43: 130
A44: 2 | B44: 立冬 | C44: 3 | D44: 500 | E44: 3000 | F44: =IF(C44>=1,VLOOKUP(R43+MAX(0,R44-R43-C44)+0,药材收益口径!$H$2:$I$222,2,FALSE),0)+IF(C44>=2,VLOOKUP(R43+MAX(0,R44-R43-C44)+1,药材收益口径!$H$2:$I$222,2,FALSE),0)+IF(C44>=3,VLOOKUP(R43+MAX(0,R44-R43-C44)+2,药材收益口径!$H$2:$I$222,2,FALSE),0)+IF(C44>=4,VLOOKUP(R43+MAX(0,R44-R43-C44)+3,药材收益口径!$H$2:$I$222,2,FALSE),0) -> 447.45709 | G44: 345.6 | H44: 0 | I44: 0 | J44: =SUM(D44:I44) -> 4293.0571 | K44: =K43+J44 -> 149591.61 | L44: 4750 | M44: =M43+L44 -> 124954.4 | N44: =J44-L44 -> -456.94291 | O44: =K44-M44 -> 24637.209 | P44: =20000+O44 -> 44637.209 | Q44: 2260 | R44: 133
A45: 2 | B45: 小雪 | C45: 3 | D45: 500 | E45: 3000 | F45: =IF(C45>=1,VLOOKUP(R44+MAX(0,R45-R44-C45)+0,药材收益口径!$H$2:$I$222,2,FALSE),0)+IF(C45>=2,VLOOKUP(R44+MAX(0,R45-R44-C45)+1,药材收益口径!$H$2:$I$222,2,FALSE),0)+IF(C45>=3,VLOOKUP(R44+MAX(0,R45-R44-C45)+2,药材收益口径!$H$2:$I$222,2,FALSE),0)+IF(C45>=4,VLOOKUP(R44+MAX(0,R45-R44-C45)+3,药材收益口径!$H$2:$I$222,2,FALSE),0) -> 447.45709 | G45: 345.6 | H45: 0 | I45: 1000 | J45: =SUM(D45:I45) -> 5293.0571 | K45: =K44+J45 -> 154884.67 | L45: 2776.4 | M45: =M44+L45 -> 127730.8 | N45: =J45-L45 -> 2516.6571 | O45: =K45-M45 -> 27153.866 | P45: =20000+O45 -> 47153.866 | Q45: 2290 | R45: 136 | S45: 014_02 沈修文治疗成功（银钱+1000）
A46: 2 | B46: 大雪 | C46: 3 | D46: 500 | E46: 3000 | F46: =IF(C46>=1,VLOOKUP(R45+MAX(0,R46-R45-C46)+0,药材收益口径!$H$2:$I$222,2,FALSE),0)+IF(C46>=2,VLOOKUP(R45+MAX(0,R46-R45-C46)+1,药材收益口径!$H$2:$I$222,2,FALSE),0)+IF(C46>=3,VLOOKUP(R45+MAX(0,R46-R45-C46)+2,药材收益口径!$H$2:$I$222,2,FALSE),0)+IF(C46>=4,VLOOKUP(R45+MAX(0,R46-R45-C46)+3,药材收益口径!$H$2:$I$222,2,FALSE),0) -> 447.45709 | G46: 345.6 | H46: 0 | I46: 0 | J46: =SUM(D46:I46) -> 4293.0571 | K46: =K45+J46 -> 159177.72 | L46: 1550 | M46: =M45+L46 -> 129280.8 | N46: =J46-L46 -> 2743.0571 | O46: =K46-M46 -> 29896.924 | P46: =20000+O46 -> 49896.924 | Q46: 2320 | R46: 139
A47: 2 | B47: 冬至 | C47: 3 | D47: 500 | E47: 3000 | F47: =IF(C47>=1,VLOOKUP(R46+MAX(0,R47-R46-C47)+0,药材收益口径!$H$2:$I$222,2,FALSE),0)+IF(C47>=2,VLOOKUP(R46+MAX(0,R47-R46-C47)+1,药材收益口径!$H$2:$I$222,2,FALSE),0)+IF(C47>=3,VLOOKUP(R46+MAX(0,R47-R46-C47)+2,药材收益口径!$H$2:$I$222,2,FALSE),0)+IF(C47>=4,VLOOKUP(R46+MAX(0,R47-R46-C47)+3,药材收益口径!$H$2:$I$222,2,FALSE),0) -> 447.45709 | G47: 345.6 | H47: 0 | I47: 0 | J47: =SUM(D47:I47) -> 4293.0571 | K47: =K46+J47 -> 163470.78 | L47: 2776.4 | M47: =M46+L47 -> 132057.2 | N47: =J47-L47 -> 1516.6571 | O47: =K47-M47 -> 31413.581 | P47: =20000+O47 -> 51413.581 | Q47: 2350 | R47: 142
A48: 2 | B48: 小寒 | C48: 3 | D48: 500 | E48: 3000 | F48: =IF(C48>=1,VLOOKUP(R47+MAX(0,R48-R47-C48)+0,药材收益口径!$H$2:$I$222,2,FALSE),0)+IF(C48>=2,VLOOKUP(R47+MAX(0,R48-R47-C48)+1,药材收益口径!$H$2:$I$222,2,FALSE),0)+IF(C48>=3,VLOOKUP(R47+MAX(0,R48-R47-C48)+2,药材收益口径!$H$2:$I$222,2,FALSE),0)+IF(C48>=4,VLOOKUP(R47+MAX(0,R48-R47-C48)+3,药材收益口径!$H$2:$I$222,2,FALSE),0) -> 447.45709 | G48: 345.6 | H48: 0 | I48: 0 | J48: =SUM(D48:I48) -> 4293.0571 | K48: =K47+J48 -> 167763.84 | L48: 1550 | M48: =M47+L48 -> 133607.2 | N48: =J48-L48 -> 2743.0571 | O48: =K48-M48 -> 34156.638 | P48: =20000+O48 -> 54156.638 | Q48: 2380 | R48: 145
A49: 2 | B49: 大寒 | C49: 3 | D49: 500 | E49: 3000 | F49: =IF(C49>=1,VLOOKUP(R48+MAX(0,R49-R48-C49)+0,药材收益口径!$H$2:$I$222,2,FALSE),0)+IF(C49>=2,VLOOKUP(R48+MAX(0,R49-R48-C49)+1,药材收益口径!$H$2:$I$222,2,FALSE),0)+IF(C49>=3,VLOOKUP(R48+MAX(0,R49-R48-C49)+2,药材收益口径!$H$2:$I$222,2,FALSE),0)+IF(C49>=4,VLOOKUP(R48+MAX(0,R49-R48-C49)+3,药材收益口径!$H$2:$I$222,2,FALSE),0) -> 447.45709 | G49: 345.6 | H49: 0 | I49: 0 | J49: =SUM(D49:I49) -> 4293.0571 | K49: =K48+J49 -> 172056.89 | L49: 3376.4 | M49: =M48+L49 -> 136983.6 | N49: =J49-L49 -> 916.65709 | O49: =K49-M49 -> 35073.295 | P49: =20000+O49 -> 55073.295 | Q49: 2410 | R49: 148

Sheet 困难
A1: 年份 | B1: 节气 | C1: 妙手回春次数 | D1: 李言闻收入 | E1: 诊费预期 | F1: 药材净收入预期 | G1: 谢仪预期 | H1: 田租 | I1: 剧情银钱奖励 | J1: 预期收入 | K1: 累计预期收入 | L1: 预期支出 | M1: 累计预期支出 | N1: 本节气收支差 | O1: 累计收支差 | P1: 含初始资金余额 | Q1: 节气末名望 | R1: 节气末心得 | S1: 剧情备注
A2: 1 | B2: 立春 | C2: 0 | D2: 0 | E2: 0 | F2: =IF(C2>=1,VLOOKUP(0+MAX(0,R2-0-C2)+0,药材收益口径!$H$2:$I$222,2,FALSE),0)+IF(C2>=2,VLOOKUP(0+MAX(0,R2-0-C2)+1,药材收益口径!$H$2:$I$222,2,FALSE),0)+IF(C2>=3,VLOOKUP(0+MAX(0,R2-0-C2)+2,药材收益口径!$H$2:$I$222,2,FALSE),0)+IF(C2>=4,VLOOKUP(0+MAX(0,R2-0-C2)+3,药材收益口径!$H$2:$I$222,2,FALSE),0) -> 0 | G2: 0 | H2: 0 | I2: 0 | J2: =SUM(D2:I2) -> 0 | K2: =J2 -> 0 | L2: =K2 -> 0 | M2: =L2 -> 0 | N2: =J2-L2 -> 0 | O2: =K2-M2 -> 0 | P2: =20000+O2 -> 20000 | Q2: 0 | R2: 0
A3: 1 | B3: 雨水 | C3: 4 | D3: 0 | E3: 80 | F3: =IF(C3>=1,VLOOKUP(R2+MAX(0,R3-R2-C3)+0,药材收益口径!$H$2:$I$222,2,FALSE),0)+IF(C3>=2,VLOOKUP(R2+MAX(0,R3-R2-C3)+1,药材收益口径!$H$2:$I$222,2,FALSE),0)+IF(C3>=3,VLOOKUP(R2+MAX(0,R3-R2-C3)+2,药材收益口径!$H$2:$I$222,2,FALSE),0)+IF(C3>=4,VLOOKUP(R2+MAX(0,R3-R2-C3)+3,药材收益口径!$H$2:$I$222,2,FALSE),0) -> 78.666667 | G3: 460.8 | H3: 0 | I3: 0 | J3: =SUM(D3:I3) -> 619.46667 | K3: =K2+J3 -> 619.46667 | L3: 2776.4 | M3: =M2+L3 -> 2776.4 | N3: =J3-L3 -> -2156.9333 | O3: =K3-M3 -> -2156.9333 | P3: =20000+O3 -> 17843.067 | Q3: 40 | R3: 4
A4: 1 | B4: 惊蛰 | C4: 4 | D4: 0 | E4: 80 | F4: =IF(C4>=1,VLOOKUP(R3+MAX(0,R4-R3-C4)+0,药材收益口径!$H$2:$I$222,2,FALSE),0)+IF(C4>=2,VLOOKUP(R3+MAX(0,R4-R3-C4)+1,药材收益口径!$H$2:$I$222,2,FALSE),0)+IF(C4>=3,VLOOKUP(R3+MAX(0,R4-R3-C4)+2,药材收益口径!$H$2:$I$222,2,FALSE),0)+IF(C4>=4,VLOOKUP(R3+MAX(0,R4-R3-C4)+3,药材收益口径!$H$2:$I$222,2,FALSE),0) -> 78.666667 | G4: 460.8 | H4: 0 | I4: 0 | J4: =SUM(D4:I4) -> 619.46667 | K4: =K3+J4 -> 1238.9333 | L4: 1550 | M4: =M3+L4 -> 4326.4 | N4: =J4-L4 -> -930.53333 | O4: =K4-M4 -> -3087.4667 | P4: =20000+O4 -> 16912.533 | Q4: 80 | R4: 8
A5: 1 | B5: 春分 | C5: 4 | D5: 0 | E5: 110 | F5: =IF(C5>=1,VLOOKUP(R4+MAX(0,R5-R4-C5)+0,药材收益口径!$H$2:$I$222,2,FALSE),0)+IF(C5>=2,VLOOKUP(R4+MAX(0,R5-R4-C5)+1,药材收益口径!$H$2:$I$222,2,FALSE),0)+IF(C5>=3,VLOOKUP(R4+MAX(0,R5-R4-C5)+2,药材收益口径!$H$2:$I$222,2,FALSE),0)+IF(C5>=4,VLOOKUP(R4+MAX(0,R5-R4-C5)+3,药材收益口径!$H$2:$I$222,2,FALSE),0) -> 227.41667 | G5: 460.8 | H5: 0 | I5: 0 | J5: =SUM(D5:I5) -> 798.21667 | K5: =K4+J5 -> 2037.15 | L5: 3376.4 | M5: =M4+L5 -> 7702.8 | N5: =J5-L5 -> -2578.1833 | O5: =K5-M5 -> -5665.65 | P5: =20000+O5 -> 14334.35 | Q5: 120 | R5: 12
A6: 1 | B6: 清明 | C6: 4 | D6: 0 | E6: 200 | F6: =IF(C6>=1,VLOOKUP(R5+MAX(0,R6-R5-C6)+0,药材收益口径!$H$2:$I$222,2,FALSE),0)+IF(C6>=2,VLOOKUP(R5+MAX(0,R6-R5-C6)+1,药材收益口径!$H$2:$I$222,2,FALSE),0)+IF(C6>=3,VLOOKUP(R5+MAX(0,R6-R5-C6)+2,药材收益口径!$H$2:$I$222,2,FALSE),0)+IF(C6>=4,VLOOKUP(R5+MAX(0,R6-R5-C6)+3,药材收益口径!$H$2:$I$222,2,FALSE),0) -> 261.1 | G6: 460.8 | H6: 0 | I6: 0 | J6: =SUM(D6:I6) -> 921.9 | K6: =K5+J6 -> 2959.05 | L6: 3550 | M6: =M5+L6 -> 11252.8 | N6: =J6-L6 -> -2628.1 | O6: =K6-M6 -> -8293.75 | P6: =20000+O6 -> 11706.25 | Q6: 160 | R6: 16
A7: 1 | B7: 谷雨 | C7: 4 | D7: 0 | E7: 200 | F7: =IF(C7>=1,VLOOKUP(R6+MAX(0,R7-R6-C7)+0,药材收益口径!$H$2:$I$222,2,FALSE),0)+IF(C7>=2,VLOOKUP(R6+MAX(0,R7-R6-C7)+1,药材收益口径!$H$2:$I$222,2,FALSE),0)+IF(C7>=3,VLOOKUP(R6+MAX(0,R7-R6-C7)+2,药材收益口径!$H$2:$I$222,2,FALSE),0)+IF(C7>=4,VLOOKUP(R6+MAX(0,R7-R6-C7)+3,药材收益口径!$H$2:$I$222,2,FALSE),0) -> 241.98333 | G7: 460.8 | H7: 0 | I7: 1000 | J7: =SUM(D7:I7) -> 1902.7833 | K7: =K6+J7 -> 4861.8333 | L7: 2776.4 | M7: =M6+L7 -> 14029.2 | N7: =J7-L7 -> -873.61667 | O7: =K7-M7 -> -9167.3667 | P7: =20000+O7 -> 10832.633 | Q7: 200 | R7: 20 | S7: 022_02 敬亭治疗成功（银钱+1000）
A8: 1 | B8: 立夏 | C8: 4 | D8: 0 | E8: 200 | F8: =IF(C8>=1,VLOOKUP(R7+MAX(0,R8-R7-C8)+0,药材收益口径!$H$2:$I$222,2,FALSE),0)+IF(C8>=2,VLOOKUP(R7+MAX(0,R8-R7-C8)+1,药材收益口径!$H$2:$I$222,2,FALSE),0)+IF(C8>=3,VLOOKUP(R7+MAX(0,R8-R7-C8)+2,药材收益口径!$H$2:$I$222,2,FALSE),0)+IF(C8>=4,VLOOKUP(R7+MAX(0,R8-R7-C8)+3,药材收益口径!$H$2:$I$222,2,FALSE),0) -> 243.0625 | G8: 460.8 | H8: 0 | I8: 0 | J8: =SUM(D8:I8) -> 903.8625 | K8: =K7+J8 -> 5765.6958 | L8: 2650 | M8: =M7+L8 -> 16679.2 | N8: =J8-L8 -> -1746.1375 | O8: =K8-M8 -> -10913.504 | P8: =20000+O8 -> 9086.4958 | Q8: 240 | R8: 24
A9: 1 | B9: 小满 | C9: 4 | D9: 0 | E9: 200 | F9: =IF(C9>=1,VLOOKUP(R8+MAX(0,R9-R8-C9)+0,药材收益口径!$H$2:$I$222,2,FALSE),0)+IF(C9>=2,VLOOKUP(R8+MAX(0,R9-R8-C9)+1,药材收益口径!$H$2:$I$222,2,FALSE),0)+IF(C9>=3,VLOOKUP(R8+MAX(0,R9-R8-C9)+2,药材收益口径!$H$2:$I$222,2,FALSE),0)+IF(C9>=4,VLOOKUP(R8+MAX(0,R9-R8-C9)+3,药材收益口径!$H$2:$I$222,2,FALSE),0) -> 432.66856 | G9: 460.8 | H9: 0 | I9: 0 | J9: =SUM(D9:I9) -> 1093.4686 | K9: =K8+J9 -> 6859.1644 | L9: 3676.4 | M9: =M8+L9 -> 20355.6 | N9: =J9-L9 -> -2582.9314 | O9: =K9-M9 -> -13496.436 | P9: =20000+O9 -> 6503.5644 | Q9: 280 | R9: 28
A10: 1 | B10: 芒种 | C10: 4 | D10: 0 | E10: 350 | F10: =IF(C10>=1,VLOOKUP(R9+MAX(0,R10-R9-C10)+0,药材收益口径!$H$2:$I$222,2,FALSE),0)+IF(C10>=2,VLOOKUP(R9+MAX(0,R10-R9-C10)+1,药材收益口径!$H$2:$I$222,2,FALSE),0)+IF(C10>=3,VLOOKUP(R9+MAX(0,R10-R9-C10)+2,药材收益口径!$H$2:$I$222,2,FALSE),0)+IF(C10>=4,VLOOKUP(R9+MAX(0,R10-R9-C10)+3,药材收益口径!$H$2:$I$222,2,FALSE),0) -> 430.92308 | G10: 460.8 | H10: 0 | I10: 0 | J10: =SUM(D10:I10) -> 1241.7231 | K10: =K9+J10 -> 8100.8875 | L10: 2450 | M10: =M9+L10 -> 22805.6 | N10: =J10-L10 -> -1208.2769 | O10: =K10-M10 -> -14704.713 | P10: =20000+O10 -> 5295.2875 | Q10: 320 | R10: 32
A11: 1 | B11: 夏至 | C11: 4 | D11: 0 | E11: 800 | F11: =IF(C11>=1,VLOOKUP(R10+MAX(0,R11-R10-C11)+0,药材收益口径!$H$2:$I$222,2,FALSE),0)+IF(C11>=2,VLOOKUP(R10+MAX(0,R11-R10-C11)+1,药材收益口径!$H$2:$I$222,2,FALSE),0)+IF(C11>=3,VLOOKUP(R10+MAX(0,R11-R10-C11)+2,药材收益口径!$H$2:$I$222,2,FALSE),0)+IF(C11>=4,VLOOKUP(R10+MAX(0,R11-R10-C11)+3,药材收益口径!$H$2:$I$222,2,FALSE),0) -> 424.33077 | G11: 460.8 | H11: 0 | I11: 0 | J11: =SUM(D11:I11) -> 1685.1308 | K11: =K10+J11 -> 9786.0182 | L11: 3676.4 | M11: =M10+L11 -> 26482 | N11: =J11-L11 -> -1991.2692 | O11: =K11-M11 -> -16695.982 | P11: =20000+O11 -> 3304.0182 | Q11: 360 | R11: 36
A12: 1 | B12: 小暑 | C12: 4 | D12: 0 | E12: 800 | F12: =IF(C12>=1,VLOOKUP(R11+MAX(0,R12-R11-C12)+0,药材收益口径!$H$2:$I$222,2,FALSE),0)+IF(C12>=2,VLOOKUP(R11+MAX(0,R12-R11-C12)+1,药材收益口径!$H$2:$I$222,2,FALSE),0)+IF(C12>=3,VLOOKUP(R11+MAX(0,R12-R11-C12)+2,药材收益口径!$H$2:$I$222,2,FALSE),0)+IF(C12>=4,VLOOKUP(R11+MAX(0,R12-R11-C12)+3,药材收益口径!$H$2:$I$222,2,FALSE),0) -> 417.40625 | G12: 460.8 | H12: 0 | I12: 0 | J12: =SUM(D12:I12) -> 1678.2062 | K12: =K11+J12 -> 11464.224 | L12: 2450 | M12: =M11+L12 -> 28932 | N12: =J12-L12 -> -771.79375 | O12: =K12-M12 -> -17467.776 | P12: =20000+O12 -> 2532.2245 | Q12: 400 | R12: 40
A13: 1 | B13: 大暑 | C13: 4 | D13: 0 | E13: 800 | F13: =IF(C13>=1,VLOOKUP(R12+MAX(0,R13-R12-C13)+0,药材收益口径!$H$2:$I$222,2,FALSE),0)+IF(C13>=2,VLOOKUP(R12+MAX(0,R13-R12-C13)+1,药材收益口径!$H$2:$I$222,2,FALSE),0)+IF(C13>=3,VLOOKUP(R12+MAX(0,R13-R12-C13)+2,药材收益口径!$H$2:$I$222,2,FALSE),0)+IF(C13>=4,VLOOKUP(R12+MAX(0,R13-R12-C13)+3,药材收益口径!$H$2:$I$222,2,FALSE),0) -> 429.88889 | G13: 460.8 | H13: 5000 | I13: 1000 | J13: =SUM(D13:I13) -> 7690.6889 | K13: =K12+J13 -> 19154.913 | L13: 3276.4 | M13: =M12+L13 -> 32208.4 | N13: =J13-L13 -> 4414.2889 | O13: =K13-M13 -> -13053.487 | P13: =20000+O13 -> 6946.5134 | Q13: 440 | R13: 44 | S13: 023_02 谢飞燕肺气虚（银钱+1000）
A14: 1 | B14: 立秋 | C14: 4 | D14: 0 | E14: 800 | F14: =IF(C14>=1,VLOOKUP(R13+MAX(0,R14-R13-C14)+0,药材收益口径!$H$2:$I$222,2,FALSE),0)+IF(C14>=2,VLOOKUP(R13+MAX(0,R14-R13-C14)+1,药材收益口径!$H$2:$I$222,2,FALSE),0)+IF(C14>=3,VLOOKUP(R13+MAX(0,R14-R13-C14)+2,药材收益口径!$H$2:$I$222,2,FALSE),0)+IF(C14>=4,VLOOKUP(R13+MAX(0,R14-R13-C14)+3,药材收益口径!$H$2:$I$222,2,FALSE),0) -> 419.89474 | G14: 460.8 | H14: 0 | I14: 1000 | J14: =SUM(D14:I14) -> 2680.6947 | K14: =K13+J14 -> 21835.608 | L14: 2650 | M14: =M13+L14 -> 34858.4 | N14: =J14-L14 -> 30.694737 | O14: =K14-M14 -> -13022.792 | P14: =20000+O14 -> 6977.2081 | Q14: 480 | R14: 48 | S14: 024_02 谢飞燕肺阴虚（银钱+1000）
A15: 1 | B15: 处暑 | C15: 4 | D15: 0 | E15: 800 | F15: =IF(C15>=1,VLOOKUP(R14+MAX(0,R15-R14-C15)+0,药材收益口径!$H$2:$I$222,2,FALSE),0)+IF(C15>=2,VLOOKUP(R14+MAX(0,R15-R14-C15)+1,药材收益口径!$H$2:$I$222,2,FALSE),0)+IF(C15>=3,VLOOKUP(R14+MAX(0,R15-R14-C15)+2,药材收益口径!$H$2:$I$222,2,FALSE),0)+IF(C15>=4,VLOOKUP(R14+MAX(0,R15-R14-C15)+3,药材收益口径!$H$2:$I$222,2,FALSE),0) -> 485.31807 | G15: 460.8 | H15: 0 | I15: 0 | J15: =SUM(D15:I15) -> 1746.1181 | K15: =K14+J15 -> 23581.726 | L15: 4776.4 | M15: =M14+L15 -> 39634.8 | N15: =J15-L15 -> -3030.2819 | O15: =K15-M15 -> -16053.074 | P15: =20000+O15 -> 3946.9262 | Q15: 520 | R15: 52
A16: 1 | B16: 白露 | C16: 4 | D16: 0 | E16: 800 | F16: =IF(C16>=1,VLOOKUP(R15+MAX(0,R16-R15-C16)+0,药材收益口径!$H$2:$I$222,2,FALSE),0)+IF(C16>=2,VLOOKUP(R15+MAX(0,R16-R15-C16)+1,药材收益口径!$H$2:$I$222,2,FALSE),0)+IF(C16>=3,VLOOKUP(R15+MAX(0,R16-R15-C16)+2,药材收益口径!$H$2:$I$222,2,FALSE),0)+IF(C16>=4,VLOOKUP(R15+MAX(0,R16-R15-C16)+3,药材收益口径!$H$2:$I$222,2,FALSE),0) -> 473.91395 | G16: 460.8 | H16: 0 | I16: 1000 | J16: =SUM(D16:I16) -> 2734.7139 | K16: =K15+J16 -> 26316.44 | L16: 1550 | M16: =M15+L16 -> 41184.8 | N16: =J16-L16 -> 1184.7139 | O16: =K16-M16 -> -14868.36 | P16: =20000+O16 -> 5131.6401 | Q16: 1560 | R16: 56 | S16: 005_02 治愈世子（银钱+1000，名望+1000）
A17: 1 | B17: 秋分 | C17: 4 | D17: 0 | E17: 2000 | F17: =IF(C17>=1,VLOOKUP(R16+MAX(0,R17-R16-C17)+0,药材收益口径!$H$2:$I$222,2,FALSE),0)+IF(C17>=2,VLOOKUP(R16+MAX(0,R17-R16-C17)+1,药材收益口径!$H$2:$I$222,2,FALSE),0)+IF(C17>=3,VLOOKUP(R16+MAX(0,R17-R16-C17)+2,药材收益口径!$H$2:$I$222,2,FALSE),0)+IF(C17>=4,VLOOKUP(R16+MAX(0,R17-R16-C17)+3,药材收益口径!$H$2:$I$222,2,FALSE),0) -> 468.78571 | G17: 460.8 | H17: 0 | I17: 0 | J17: =SUM(D17:I17) -> 2929.5857 | K17: =K16+J17 -> 29246.026 | L17: 3376.4 | M17: =M16+L17 -> 44561.2 | N17: =J17-L17 -> -446.81429 | O17: =K17-M17 -> -15315.174 | P17: =20000+O17 -> 4684.8259 | Q17: 1600 | R17: 67 | S17: 024_04 王百堂来访（心得+7）
A18: 1 | B18: 寒露 | C18: 4 | D18: 0 | E18: 2000 | F18: =IF(C18>=1,VLOOKUP(R17+MAX(0,R18-R17-C18)+0,药材收益口径!$H$2:$I$222,2,FALSE),0)+IF(C18>=2,VLOOKUP(R17+MAX(0,R18-R17-C18)+1,药材收益口径!$H$2:$I$222,2,FALSE),0)+IF(C18>=3,VLOOKUP(R17+MAX(0,R18-R17-C18)+2,药材收益口径!$H$2:$I$222,2,FALSE),0)+IF(C18>=4,VLOOKUP(R17+MAX(0,R18-R17-C18)+3,药材收益口径!$H$2:$I$222,2,FALSE),0) -> 497.17241 | G18: 460.8 | H18: 0 | I18: 0 | J18: =SUM(D18:I18) -> 2957.9724 | K18: =K17+J18 -> 32203.998 | L18: 1550 | M18: =M17+L18 -> 46111.2 | N18: =J18-L18 -> 1407.9724 | O18: =K18-M18 -> -13907.202 | P18: =20000+O18 -> 6092.7983 | Q18: 1640 | R18: 71
A19: 1 | B19: 霜降 | C19: 4 | D19: 0 | E19: 2000 | F19: =IF(C19>=1,VLOOKUP(R18+MAX(0,R19-R18-C19)+0,药材收益口径!$H$2:$I$222,2,FALSE),0)+IF(C19>=2,VLOOKUP(R18+MAX(0,R19-R18-C19)+1,药材收益口径!$H$2:$I$222,2,FALSE),0)+IF(C19>=3,VLOOKUP(R18+MAX(0,R19-R18-C19)+2,药材收益口径!$H$2:$I$222,2,FALSE),0)+IF(C19>=4,VLOOKUP(R18+MAX(0,R19-R18-C19)+3,药材收益口径!$H$2:$I$222,2,FALSE),0) -> 490.72859 | G19: 460.8 | H19: 15000 | I19: 0 | J19: =SUM(D19:I19) -> 17951.529 | K19: =K18+J19 -> 50155.527 | L19: 4276.4 | M19: =M18+L19 -> 50387.6 | N19: =J19-L19 -> 13675.129 | O19: =K19-M19 -> -232.07315 | P19: =20000+O19 -> 19767.927 | Q19: 1680 | R19: 75
A20: 1 | B20: 立冬 | C20: 4 | D20: 0 | E20: 2000 | F20: =IF(C20>=1,VLOOKUP(R19+MAX(0,R20-R19-C20)+0,药材收益口径!$H$2:$I$222,2,FALSE),0)+IF(C20>=2,VLOOKUP(R19+MAX(0,R20-R19-C20)+1,药材收益口径!$H$2:$I$222,2,FALSE),0)+IF(C20>=3,VLOOKUP(R19+MAX(0,R20-R19-C20)+2,药材收益口径!$H$2:$I$222,2,FALSE),0)+IF(C20>=4,VLOOKUP(R19+MAX(0,R20-R19-C20)+3,药材收益口径!$H$2:$I$222,2,FALSE),0) -> 576.99401 | G20: 460.8 | H20: 0 | I20: 0 | J20: =SUM(D20:I20) -> 3037.794 | K20: =K19+J20 -> 53193.321 | L20: 4750 | M20: =M19+L20 -> 55137.6 | N20: =J20-L20 -> -1712.206 | O20: =K20-M20 -> -1944.2791 | P20: =20000+O20 -> 18055.721 | Q20: 1720 | R20: 79
A21: 1 | B21: 小雪 | C21: 4 | D21: 0 | E21: 2000 | F21: =IF(C21>=1,VLOOKUP(R20+MAX(0,R21-R20-C21)+0,药材收益口径!$H$2:$I$222,2,FALSE),0)+IF(C21>=2,VLOOKUP(R20+MAX(0,R21-R20-C21)+1,药材收益口径!$H$2:$I$222,2,FALSE),0)+IF(C21>=3,VLOOKUP(R20+MAX(0,R21-R20-C21)+2,药材收益口径!$H$2:$I$222,2,FALSE),0)+IF(C21>=4,VLOOKUP(R20+MAX(0,R21-R20-C21)+3,药材收益口径!$H$2:$I$222,2,FALSE),0) -> 594.8479 | G21: 460.8 | H21: 0 | I21: 0 | J21: =SUM(D21:I21) -> 3055.6479 | K21: =K20+J21 -> 56248.969 | L21: 2776.4 | M21: =M20+L21 -> 57914 | N21: =J21-L21 -> 279.2479 | O21: =K21-M21 -> -1665.0312 | P21: =20000+O21 -> 18334.969 | Q21: 1760 | R21: 83
A22: 1 | B22: 大雪 | C22: 4 | D22: 0 | E22: 2000 | F22: =IF(C22>=1,VLOOKUP(R21+MAX(0,R22-R21-C22)+0,药材收益口径!$H$2:$I$222,2,FALSE),0)+IF(C22>=2,VLOOKUP(R21+MAX(0,R22-R21-C22)+1,药材收益口径!$H$2:$I$222,2,FALSE),0)+IF(C22>=3,VLOOKUP(R21+MAX(0,R22-R21-C22)+2,药材收益口径!$H$2:$I$222,2,FALSE),0)+IF(C22>=4,VLOOKUP(R21+MAX(0,R22-R21-C22)+3,药材收益口径!$H$2:$I$222,2,FALSE),0) -> 587.74613 | G22: 460.8 | H22: 0 | I22: 0 | J22: =SUM(D22:I22) -> 3048.5461 | K22: =K21+J22 -> 59297.515 | L22: 1550 | M22: =M21+L22 -> 59464 | N22: =J22-L22 -> 1498.5461 | O22: =K22-M22 -> -166.48511 | P22: =20000+O22 -> 19833.515 | Q22: 1800 | R22: 87
A23: 1 | B23: 冬至 | C23: 4 | D23: 0 | E23: 2000 | F23: =IF(C23>=1,VLOOKUP(R22+MAX(0,R23-R22-C23)+0,药材收益口径!$H$2:$I$222,2,FALSE),0)+IF(C23>=2,VLOOKUP(R22+MAX(0,R23-R22-C23)+1,药材收益口径!$H$2:$I$222,2,FALSE),0)+IF(C23>=3,VLOOKUP(R22+MAX(0,R23-R22-C23)+2,药材收益口径!$H$2:$I$222,2,FALSE),0)+IF(C23>=4,VLOOKUP(R22+MAX(0,R23-R22-C23)+3,药材收益口径!$H$2:$I$222,2,FALSE),0) -> 573.40435 | G23: 460.8 | H23: 0 | I23: 0 | J23: =SUM(D23:I23) -> 3034.2043 | K23: =K22+J23 -> 62331.719 | L23: 2776.4 | M23: =M22+L23 -> 62240.4 | N23: =J23-L23 -> 257.80435 | O23: =K23-M23 -> 91.319241 | P23: =20000+O23 -> 20091.319 | Q23: 1840 | R23: 91
A24: 1 | B24: 小寒 | C24: 4 | D24: 0 | E24: 2000 | F24: =IF(C24>=1,VLOOKUP(R23+MAX(0,R24-R23-C24)+0,药材收益口径!$H$2:$I$222,2,FALSE),0)+IF(C24>=2,VLOOKUP(R23+MAX(0,R24-R23-C24)+1,药材收益口径!$H$2:$I$222,2,FALSE),0)+IF(C24>=3,VLOOKUP(R23+MAX(0,R24-R23-C24)+2,药材收益口径!$H$2:$I$222,2,FALSE),0)+IF(C24>=4,VLOOKUP(R23+MAX(0,R24-R23-C24)+3,药材收益口径!$H$2:$I$222,2,FALSE),0) -> 579.34545 | G24: 460.8 | H24: 0 | I24: 0 | J24: =SUM(D24:I24) -> 3040.1454 | K24: =K23+J24 -> 65371.865 | L24: 1550 | M24: =M23+L24 -> 63790.4 | N24: =J24-L24 -> 1490.1454 | O24: =K24-M24 -> 1581.4647 | P24: =20000+O24 -> 21581.465 | Q24: 1880 | R24: 95
A25: 1 | B25: 大寒 | C25: 4 | D25: 0 | E25: 2000 | F25: =IF(C25>=1,VLOOKUP(R24+MAX(0,R25-R24-C25)+0,药材收益口径!$H$2:$I$222,2,FALSE),0)+IF(C25>=2,VLOOKUP(R24+MAX(0,R25-R24-C25)+1,药材收益口径!$H$2:$I$222,2,FALSE),0)+IF(C25>=3,VLOOKUP(R24+MAX(0,R25-R24-C25)+2,药材收益口径!$H$2:$I$222,2,FALSE),0)+IF(C25>=4,VLOOKUP(R24+MAX(0,R25-R24-C25)+3,药材收益口径!$H$2:$I$222,2,FALSE),0) -> 577.66035 | G25: 460.8 | H25: 0 | I25: 0 | J25: =SUM(D25:I25) -> 3038.4604 | K25: =K24+J25 -> 68410.325 | L25: 3376.4 | M25: =M24+L25 -> 67166.8 | N25: =J25-L25 -> -337.93965 | O25: =K25-M25 -> 1243.525 | P25: =20000+O25 -> 21243.525 | Q25: 1920 | R25: 99
A26: 2 | B26: 立春 | C26: 4 | D26: 0 | E26: 2000 | F26: =IF(C26>=1,VLOOKUP(R25+MAX(0,R26-R25-C26)+0,药材收益口径!$H$2:$I$222,2,FALSE),0)+IF(C26>=2,VLOOKUP(R25+MAX(0,R26-R25-C26)+1,药材收益口径!$H$2:$I$222,2,FALSE),0)+IF(C26>=3,VLOOKUP(R25+MAX(0,R26-R25-C26)+2,药材收益口径!$H$2:$I$222,2,FALSE),0)+IF(C26>=4,VLOOKUP(R25+MAX(0,R26-R25-C26)+3,药材收益口径!$H$2:$I$222,2,FALSE),0) -> 591.77778 | G26: 460.8 | H26: 0 | I26: 2000 | J26: =SUM(D26:I26) -> 5052.5778 | K26: =K25+J26 -> 73462.903 | L26: 2650 | M26: =M25+L26 -> 69816.8 | N26: =J26-L26 -> 2402.5778 | O26: =K26-M26 -> 3646.1028 | P26: =20000+O26 -> 23646.103 | Q26: 1960 | R26: 103 | S26: 025_02 和尚肾精不足（银钱+2000）
A27: 2 | B27: 雨水 | C27: 4 | D27: 0 | E27: 2000 | F27: =IF(C27>=1,VLOOKUP(R26+MAX(0,R27-R26-C27)+0,药材收益口径!$H$2:$I$222,2,FALSE),0)+IF(C27>=2,VLOOKUP(R26+MAX(0,R27-R26-C27)+1,药材收益口径!$H$2:$I$222,2,FALSE),0)+IF(C27>=3,VLOOKUP(R26+MAX(0,R27-R26-C27)+2,药材收益口径!$H$2:$I$222,2,FALSE),0)+IF(C27>=4,VLOOKUP(R26+MAX(0,R27-R26-C27)+3,药材收益口径!$H$2:$I$222,2,FALSE),0) -> 599.15421 | G27: 460.8 | H27: 0 | I27: 0 | J27: =SUM(D27:I27) -> 3059.9542 | K27: =K26+J27 -> 76522.857 | L27: 2776.4 | M27: =M26+L27 -> 72593.2 | N27: =J27-L27 -> 283.55421 | O27: =K27-M27 -> 3929.657 | P27: =20000+O27 -> 23929.657 | Q27: 2000 | R27: 107
A28: 2 | B28: 惊蛰 | C28: 4 | D28: 0 | E28: 3500 | F28: =IF(C28>=1,VLOOKUP(R27+MAX(0,R28-R27-C28)+0,药材收益口径!$H$2:$I$222,2,FALSE),0)+IF(C28>=2,VLOOKUP(R27+MAX(0,R28-R27-C28)+1,药材收益口径!$H$2:$I$222,2,FALSE),0)+IF(C28>=3,VLOOKUP(R27+MAX(0,R28-R27-C28)+2,药材收益口径!$H$2:$I$222,2,FALSE),0)+IF(C28>=4,VLOOKUP(R27+MAX(0,R28-R27-C28)+3,药材收益口径!$H$2:$I$222,2,FALSE),0) -> 596.60946 | G28: 460.8 | H28: 0 | I28: 0 | J28: =SUM(D28:I28) -> 4557.4095 | K28: =K27+J28 -> 81080.266 | L28: 1550 | M28: =M27+L28 -> 74143.2 | N28: =J28-L28 -> 3007.4095 | O28: =K28-M28 -> 6937.0665 | P28: =20000+O28 -> 26937.066 | Q28: 2040 | R28: 111
A29: 2 | B29: 春分 | C29: 4 | D29: 0 | E29: 4000 | F29: =IF(C29>=1,VLOOKUP(R28+MAX(0,R29-R28-C29)+0,药材收益口径!$H$2:$I$222,2,FALSE),0)+IF(C29>=2,VLOOKUP(R28+MAX(0,R29-R28-C29)+1,药材收益口径!$H$2:$I$222,2,FALSE),0)+IF(C29>=3,VLOOKUP(R28+MAX(0,R29-R28-C29)+2,药材收益口径!$H$2:$I$222,2,FALSE),0)+IF(C29>=4,VLOOKUP(R28+MAX(0,R29-R28-C29)+3,药材收益口径!$H$2:$I$222,2,FALSE),0) -> 596.60946 | G29: 460.8 | H29: 0 | I29: 0 | J29: =SUM(D29:I29) -> 5057.4095 | K29: =K28+J29 -> 86137.676 | L29: 3376.4 | M29: =M28+L29 -> 77519.6 | N29: =J29-L29 -> 1681.0095 | O29: =K29-M29 -> 8618.0759 | P29: =20000+O29 -> 28618.076 | Q29: 2080 | R29: 115
A30: 2 | B30: 清明 | C30: 4 | D30: 0 | E30: 4000 | F30: =IF(C30>=1,VLOOKUP(R29+MAX(0,R30-R29-C30)+0,药材收益口径!$H$2:$I$222,2,FALSE),0)+IF(C30>=2,VLOOKUP(R29+MAX(0,R30-R29-C30)+1,药材收益口径!$H$2:$I$222,2,FALSE),0)+IF(C30>=3,VLOOKUP(R29+MAX(0,R30-R29-C30)+2,药材收益口径!$H$2:$I$222,2,FALSE),0)+IF(C30>=4,VLOOKUP(R29+MAX(0,R30-R29-C30)+3,药材收益口径!$H$2:$I$222,2,FALSE),0) -> 596.60946 | G30: 460.8 | H30: 0 | I30: 0 | J30: =SUM(D30:I30) -> 5057.4095 | K30: =K29+J30 -> 91195.085 | L30: 3550 | M30: =M29+L30 -> 81069.6 | N30: =J30-L30 -> 1507.4095 | O30: =K30-M30 -> 10125.485 | P30: =20000+O30 -> 30125.485 | Q30: 2120 | R30: 119
A31: 2 | B31: 谷雨 | C31: 4 | D31: 0 | E31: 4000 | F31: =IF(C31>=1,VLOOKUP(R30+MAX(0,R31-R30-C31)+0,药材收益口径!$H$2:$I$222,2,FALSE),0)+IF(C31>=2,VLOOKUP(R30+MAX(0,R31-R30-C31)+1,药材收益口径!$H$2:$I$222,2,FALSE),0)+IF(C31>=3,VLOOKUP(R30+MAX(0,R31-R30-C31)+2,药材收益口径!$H$2:$I$222,2,FALSE),0)+IF(C31>=4,VLOOKUP(R30+MAX(0,R31-R30-C31)+3,药材收益口径!$H$2:$I$222,2,FALSE),0) -> 596.60946 | G31: 460.8 | H31: 0 | I31: 0 | J31: =SUM(D31:I31) -> 5057.4095 | K31: =K30+J31 -> 96252.495 | L31: 2776.4 | M31: =M30+L31 -> 83846 | N31: =J31-L31 -> 2281.0095 | O31: =K31-M31 -> 12406.495 | P31: =20000+O31 -> 32406.495 | Q31: 2160 | R31: 123
A32: 2 | B32: 立夏 | C32: 4 | D32: 0 | E32: 4000 | F32: =IF(C32>=1,VLOOKUP(R31+MAX(0,R32-R31-C32)+0,药材收益口径!$H$2:$I$222,2,FALSE),0)+IF(C32>=2,VLOOKUP(R31+MAX(0,R32-R31-C32)+1,药材收益口径!$H$2:$I$222,2,FALSE),0)+IF(C32>=3,VLOOKUP(R31+MAX(0,R32-R31-C32)+2,药材收益口径!$H$2:$I$222,2,FALSE),0)+IF(C32>=4,VLOOKUP(R31+MAX(0,R32-R31-C32)+3,药材收益口径!$H$2:$I$222,2,FALSE),0) -> 596.60946 | G32: 460.8 | H32: 0 | I32: 0 | J32: =SUM(D32:I32) -> 5057.4095 | K32: =K31+J32 -> 101309.9 | L32: 2650 | M32: =M31+L32 -> 86496 | N32: =J32-L32 -> 2407.4095 | O32: =K32-M32 -> 14813.904 | P32: =20000+O32 -> 34813.904 | Q32: 2200 | R32: 127
A33: 2 | B33: 小满 | C33: 4 | D33: 0 | E33: 4000 | F33: =IF(C33>=1,VLOOKUP(R32+MAX(0,R33-R32-C33)+0,药材收益口径!$H$2:$I$222,2,FALSE),0)+IF(C33>=2,VLOOKUP(R32+MAX(0,R33-R32-C33)+1,药材收益口径!$H$2:$I$222,2,FALSE),0)+IF(C33>=3,VLOOKUP(R32+MAX(0,R33-R32-C33)+2,药材收益口径!$H$2:$I$222,2,FALSE),0)+IF(C33>=4,VLOOKUP(R32+MAX(0,R33-R32-C33)+3,药材收益口径!$H$2:$I$222,2,FALSE),0) -> 596.60946 | G33: 460.8 | H33: 0 | I33: 0 | J33: =SUM(D33:I33) -> 5057.4095 | K33: =K32+J33 -> 106367.31 | L33: 3676.4 | M33: =M32+L33 -> 90172.4 | N33: =J33-L33 -> 1381.0095 | O33: =K33-M33 -> 16194.914 | P33: =20000+O33 -> 36194.914 | Q33: 2240 | R33: 131
A34: 2 | B34: 芒种 | C34: 4 | D34: 0 | E34: 4000 | F34: =IF(C34>=1,VLOOKUP(R33+MAX(0,R34-R33-C34)+0,药材收益口径!$H$2:$I$222,2,FALSE),0)+IF(C34>=2,VLOOKUP(R33+MAX(0,R34-R33-C34)+1,药材收益口径!$H$2:$I$222,2,FALSE),0)+IF(C34>=3,VLOOKUP(R33+MAX(0,R34-R33-C34)+2,药材收益口径!$H$2:$I$222,2,FALSE),0)+IF(C34>=4,VLOOKUP(R33+MAX(0,R34-R33-C34)+3,药材收益口径!$H$2:$I$222,2,FALSE),0) -> 596.60946 | G34: 460.8 | H34: 0 | I34: 0 | J34: =SUM(D34:I34) -> 5057.4095 | K34: =K33+J34 -> 111424.72 | L34: 2450 | M34: =M33+L34 -> 92622.4 | N34: =J34-L34 -> 2607.4095 | O34: =K34-M34 -> 18802.323 | P34: =20000+O34 -> 38802.323 | Q34: 2280 | R34: 135
A35: 2 | B35: 夏至 | C35: 4 | D35: 0 | E35: 4000 | F35: =IF(C35>=1,VLOOKUP(R34+MAX(0,R35-R34-C35)+0,药材收益口径!$H$2:$I$222,2,FALSE),0)+IF(C35>=2,VLOOKUP(R34+MAX(0,R35-R34-C35)+1,药材收益口径!$H$2:$I$222,2,FALSE),0)+IF(C35>=3,VLOOKUP(R34+MAX(0,R35-R34-C35)+2,药材收益口径!$H$2:$I$222,2,FALSE),0)+IF(C35>=4,VLOOKUP(R34+MAX(0,R35-R34-C35)+3,药材收益口径!$H$2:$I$222,2,FALSE),0) -> 596.60946 | G35: 460.8 | H35: 0 | I35: 0 | J35: =SUM(D35:I35) -> 5057.4095 | K35: =K34+J35 -> 116482.13 | L35: 3676.4 | M35: =M34+L35 -> 96298.8 | N35: =J35-L35 -> 1381.0095 | O35: =K35-M35 -> 20183.333 | P35: =20000+O35 -> 40183.333 | Q35: 2320 | R35: 139
A36: 2 | B36: 小暑 | C36: 4 | D36: 0 | E36: 4000 | F36: =IF(C36>=1,VLOOKUP(R35+MAX(0,R36-R35-C36)+0,药材收益口径!$H$2:$I$222,2,FALSE),0)+IF(C36>=2,VLOOKUP(R35+MAX(0,R36-R35-C36)+1,药材收益口径!$H$2:$I$222,2,FALSE),0)+IF(C36>=3,VLOOKUP(R35+MAX(0,R36-R35-C36)+2,药材收益口径!$H$2:$I$222,2,FALSE),0)+IF(C36>=4,VLOOKUP(R35+MAX(0,R36-R35-C36)+3,药材收益口径!$H$2:$I$222,2,FALSE),0) -> 596.60946 | G36: 460.8 | H36: 0 | I36: 0 | J36: =SUM(D36:I36) -> 5057.4095 | K36: =K35+J36 -> 121539.54 | L36: 2450 | M36: =M35+L36 -> 98748.8 | N36: =J36-L36 -> 2607.4095 | O36: =K36-M36 -> 22790.742 | P36: =20000+O36 -> 42790.742 | Q36: 2360 | R36: 143
A37: 2 | B37: 大暑 | C37: 4 | D37: 0 | E37: 4000 | F37: =IF(C37>=1,VLOOKUP(R36+MAX(0,R37-R36-C37)+0,药材收益口径!$H$2:$I$222,2,FALSE),0)+IF(C37>=2,VLOOKUP(R36+MAX(0,R37-R36-C37)+1,药材收益口径!$H$2:$I$222,2,FALSE),0)+IF(C37>=3,VLOOKUP(R36+MAX(0,R37-R36-C37)+2,药材收益口径!$H$2:$I$222,2,FALSE),0)+IF(C37>=4,VLOOKUP(R36+MAX(0,R37-R36-C37)+3,药材收益口径!$H$2:$I$222,2,FALSE),0) -> 596.60946 | G37: 460.8 | H37: 5000 | I37: 0 | J37: =SUM(D37:I37) -> 10057.409 | K37: =K36+J37 -> 131596.95 | L37: 3276.4 | M37: =M36+L37 -> 102025.2 | N37: =J37-L37 -> 6781.0095 | O37: =K37-M37 -> 29571.752 | P37: =20000+O37 -> 49571.752 | Q37: 2400 | R37: 147
A38: 2 | B38: 立秋 | C38: 4 | D38: 0 | E38: 4000 | F38: =IF(C38>=1,VLOOKUP(R37+MAX(0,R38-R37-C38)+0,药材收益口径!$H$2:$I$222,2,FALSE),0)+IF(C38>=2,VLOOKUP(R37+MAX(0,R38-R37-C38)+1,药材收益口径!$H$2:$I$222,2,FALSE),0)+IF(C38>=3,VLOOKUP(R37+MAX(0,R38-R37-C38)+2,药材收益口径!$H$2:$I$222,2,FALSE),0)+IF(C38>=4,VLOOKUP(R37+MAX(0,R38-R37-C38)+3,药材收益口径!$H$2:$I$222,2,FALSE),0) -> 596.60946 | G38: 460.8 | H38: 0 | I38: 1000 | J38: =SUM(D38:I38) -> 6057.4095 | K38: =K37+J38 -> 137654.36 | L38: 2650 | M38: =M37+L38 -> 104675.2 | N38: =J38-L38 -> 3407.4095 | O38: =K38-M38 -> 32979.161 | P38: =20000+O38 -> 52979.161 | Q38: 2440 | R38: 151 | S38: 014_02 沈修文治疗成功（银钱+1000）
A39: 2 | B39: 处暑 | C39: 4 | D39: 0 | E39: 4000 | F39: =IF(C39>=1,VLOOKUP(R38+MAX(0,R39-R38-C39)+0,药材收益口径!$H$2:$I$222,2,FALSE),0)+IF(C39>=2,VLOOKUP(R38+MAX(0,R39-R38-C39)+1,药材收益口径!$H$2:$I$222,2,FALSE),0)+IF(C39>=3,VLOOKUP(R38+MAX(0,R39-R38-C39)+2,药材收益口径!$H$2:$I$222,2,FALSE),0)+IF(C39>=4,VLOOKUP(R38+MAX(0,R39-R38-C39)+3,药材收益口径!$H$2:$I$222,2,FALSE),0) -> 596.60946 | G39: 460.8 | H39: 0 | I39: 0 | J39: =SUM(D39:I39) -> 5057.4095 | K39: =K38+J39 -> 142711.77 | L39: 4776.4 | M39: =M38+L39 -> 109451.6 | N39: =J39-L39 -> 281.00946 | O39: =K39-M39 -> 33260.171 | P39: =20000+O39 -> 53260.171 | Q39: 2480 | R39: 155
A40: 2 | B40: 白露 | C40: 4 | D40: 0 | E40: 4000 | F40: =IF(C40>=1,VLOOKUP(R39+MAX(0,R40-R39-C40)+0,药材收益口径!$H$2:$I$222,2,FALSE),0)+IF(C40>=2,VLOOKUP(R39+MAX(0,R40-R39-C40)+1,药材收益口径!$H$2:$I$222,2,FALSE),0)+IF(C40>=3,VLOOKUP(R39+MAX(0,R40-R39-C40)+2,药材收益口径!$H$2:$I$222,2,FALSE),0)+IF(C40>=4,VLOOKUP(R39+MAX(0,R40-R39-C40)+3,药材收益口径!$H$2:$I$222,2,FALSE),0) -> 596.60946 | G40: 460.8 | H40: 0 | I40: 0 | J40: =SUM(D40:I40) -> 5057.4095 | K40: =K39+J40 -> 147769.18 | L40: 1550 | M40: =M39+L40 -> 111001.6 | N40: =J40-L40 -> 3507.4095 | O40: =K40-M40 -> 36767.58 | P40: =20000+O40 -> 56767.58 | Q40: 2520 | R40: 159
A41: 2 | B41: 秋分 | C41: 4 | D41: 0 | E41: 4000 | F41: =IF(C41>=1,VLOOKUP(R40+MAX(0,R41-R40-C41)+0,药材收益口径!$H$2:$I$222,2,FALSE),0)+IF(C41>=2,VLOOKUP(R40+MAX(0,R41-R40-C41)+1,药材收益口径!$H$2:$I$222,2,FALSE),0)+IF(C41>=3,VLOOKUP(R40+MAX(0,R41-R40-C41)+2,药材收益口径!$H$2:$I$222,2,FALSE),0)+IF(C41>=4,VLOOKUP(R40+MAX(0,R41-R40-C41)+3,药材收益口径!$H$2:$I$222,2,FALSE),0) -> 596.60946 | G41: 460.8 | H41: 0 | I41: 0 | J41: =SUM(D41:I41) -> 5057.4095 | K41: =K40+J41 -> 152826.59 | L41: 3376.4 | M41: =M40+L41 -> 114378 | N41: =J41-L41 -> 1681.0095 | O41: =K41-M41 -> 38448.589 | P41: =20000+O41 -> 58448.589 | Q41: 2560 | R41: 163
A42: 2 | B42: 寒露 | C42: 4 | D42: 0 | E42: 4000 | F42: =IF(C42>=1,VLOOKUP(R41+MAX(0,R42-R41-C42)+0,药材收益口径!$H$2:$I$222,2,FALSE),0)+IF(C42>=2,VLOOKUP(R41+MAX(0,R42-R41-C42)+1,药材收益口径!$H$2:$I$222,2,FALSE),0)+IF(C42>=3,VLOOKUP(R41+MAX(0,R42-R41-C42)+2,药材收益口径!$H$2:$I$222,2,FALSE),0)+IF(C42>=4,VLOOKUP(R41+MAX(0,R42-R41-C42)+3,药材收益口径!$H$2:$I$222,2,FALSE),0) -> 596.60946 | G42: 460.8 | H42: 0 | I42: 0 | J42: =SUM(D42:I42) -> 5057.4095 | K42: =K41+J42 -> 157884 | L42: 1550 | M42: =M41+L42 -> 115928 | N42: =J42-L42 -> 3507.4095 | O42: =K42-M42 -> 41955.999 | P42: =20000+O42 -> 61955.999 | Q42: 2600 | R42: 167
A43: 2 | B43: 霜降 | C43: 4 | D43: 0 | E43: 4000 | F43: =IF(C43>=1,VLOOKUP(R42+MAX(0,R43-R42-C43)+0,药材收益口径!$H$2:$I$222,2,FALSE),0)+IF(C43>=2,VLOOKUP(R42+MAX(0,R43-R42-C43)+1,药材收益口径!$H$2:$I$222,2,FALSE),0)+IF(C43>=3,VLOOKUP(R42+MAX(0,R43-R42-C43)+2,药材收益口径!$H$2:$I$222,2,FALSE),0)+IF(C43>=4,VLOOKUP(R42+MAX(0,R43-R42-C43)+3,药材收益口径!$H$2:$I$222,2,FALSE),0) -> 596.60946 | G43: 460.8 | H43: 15000 | I43: 1000 | J43: =SUM(D43:I43) -> 21057.409 | K43: =K42+J43 -> 178941.41 | L43: 4276.4 | M43: =M42+L43 -> 120204.4 | N43: =J43-L43 -> 16781.009 | O43: =K43-M43 -> 58737.008 | P43: =20000+O43 -> 78737.008 | Q43: 2640 | R43: 171 | S43: 017_02 杨善泉治疗成功（银钱+1000）
A44: 2 | B44: 立冬 | C44: 4 | D44: 0 | E44: 4000 | F44: =IF(C44>=1,VLOOKUP(R43+MAX(0,R44-R43-C44)+0,药材收益口径!$H$2:$I$222,2,FALSE),0)+IF(C44>=2,VLOOKUP(R43+MAX(0,R44-R43-C44)+1,药材收益口径!$H$2:$I$222,2,FALSE),0)+IF(C44>=3,VLOOKUP(R43+MAX(0,R44-R43-C44)+2,药材收益口径!$H$2:$I$222,2,FALSE),0)+IF(C44>=4,VLOOKUP(R43+MAX(0,R44-R43-C44)+3,药材收益口径!$H$2:$I$222,2,FALSE),0) -> 596.60946 | G44: 460.8 | H44: 0 | I44: 0 | J44: =SUM(D44:I44) -> 5057.4095 | K44: =K43+J44 -> 183998.82 | L44: 4750 | M44: =M43+L44 -> 124954.4 | N44: =J44-L44 -> 307.40946 | O44: =K44-M44 -> 59044.418 | P44: =20000+O44 -> 79044.418 | Q44: 2680 | R44: 175
A45: 2 | B45: 小雪 | C45: 4 | D45: 0 | E45: 4000 | F45: =IF(C45>=1,VLOOKUP(R44+MAX(0,R45-R44-C45)+0,药材收益口径!$H$2:$I$222,2,FALSE),0)+IF(C45>=2,VLOOKUP(R44+MAX(0,R45-R44-C45)+1,药材收益口径!$H$2:$I$222,2,FALSE),0)+IF(C45>=3,VLOOKUP(R44+MAX(0,R45-R44-C45)+2,药材收益口径!$H$2:$I$222,2,FALSE),0)+IF(C45>=4,VLOOKUP(R44+MAX(0,R45-R44-C45)+3,药材收益口径!$H$2:$I$222,2,FALSE),0) -> 596.60946 | G45: 460.8 | H45: 0 | I45: 0 | J45: =SUM(D45:I45) -> 5057.4095 | K45: =K44+J45 -> 189056.23 | L45: 2776.4 | M45: =M44+L45 -> 127730.8 | N45: =J45-L45 -> 2281.0095 | O45: =K45-M45 -> 61325.427 | P45: =20000+O45 -> 81325.427 | Q45: 2720 | R45: 179
A46: 2 | B46: 大雪 | C46: 4 | D46: 0 | E46: 4000 | F46: =IF(C46>=1,VLOOKUP(R45+MAX(0,R46-R45-C46)+0,药材收益口径!$H$2:$I$222,2,FALSE),0)+IF(C46>=2,VLOOKUP(R45+MAX(0,R46-R45-C46)+1,药材收益口径!$H$2:$I$222,2,FALSE),0)+IF(C46>=3,VLOOKUP(R45+MAX(0,R46-R45-C46)+2,药材收益口径!$H$2:$I$222,2,FALSE),0)+IF(C46>=4,VLOOKUP(R45+MAX(0,R46-R45-C46)+3,药材收益口径!$H$2:$I$222,2,FALSE),0) -> 596.60946 | G46: 460.8 | H46: 0 | I46: 0 | J46: =SUM(D46:I46) -> 5057.4095 | K46: =K45+J46 -> 194113.64 | L46: 1550 | M46: =M45+L46 -> 129280.8 | N46: =J46-L46 -> 3507.4095 | O46: =K46-M46 -> 64832.837 | P46: =20000+O46 -> 84832.837 | Q46: 2760 | R46: 183
A47: 2 | B47: 冬至 | C47: 4 | D47: 0 | E47: 4000 | F47: =IF(C47>=1,VLOOKUP(R46+MAX(0,R47-R46-C47)+0,药材收益口径!$H$2:$I$222,2,FALSE),0)+IF(C47>=2,VLOOKUP(R46+MAX(0,R47-R46-C47)+1,药材收益口径!$H$2:$I$222,2,FALSE),0)+IF(C47>=3,VLOOKUP(R46+MAX(0,R47-R46-C47)+2,药材收益口径!$H$2:$I$222,2,FALSE),0)+IF(C47>=4,VLOOKUP(R46+MAX(0,R47-R46-C47)+3,药材收益口径!$H$2:$I$222,2,FALSE),0) -> 596.60946 | G47: 460.8 | H47: 0 | I47: 0 | J47: =SUM(D47:I47) -> 5057.4095 | K47: =K46+J47 -> 199171.05 | L47: 2776.4 | M47: =M46+L47 -> 132057.2 | N47: =J47-L47 -> 2281.0095 | O47: =K47-M47 -> 67113.846 | P47: =20000+O47 -> 87113.846 | Q47: 2800 | R47: 187
A48: 2 | B48: 小寒 | C48: 4 | D48: 0 | E48: 4000 | F48: =IF(C48>=1,VLOOKUP(R47+MAX(0,R48-R47-C48)+0,药材收益口径!$H$2:$I$222,2,FALSE),0)+IF(C48>=2,VLOOKUP(R47+MAX(0,R48-R47-C48)+1,药材收益口径!$H$2:$I$222,2,FALSE),0)+IF(C48>=3,VLOOKUP(R47+MAX(0,R48-R47-C48)+2,药材收益口径!$H$2:$I$222,2,FALSE),0)+IF(C48>=4,VLOOKUP(R47+MAX(0,R48-R47-C48)+3,药材收益口径!$H$2:$I$222,2,FALSE),0) -> 596.60946 | G48: 460.8 | H48: 0 | I48: 0 | J48: =SUM(D48:I48) -> 5057.4095 | K48: =K47+J48 -> 204228.46 | L48: 1550 | M48: =M47+L48 -> 133607.2 | N48: =J48-L48 -> 3507.4095 | O48: =K48-M48 -> 70621.256 | P48: =20000+O48 -> 90621.256 | Q48: 2840 | R48: 191
A49: 2 | B49: 大寒 | C49: 4 | D49: 0 | E49: 4000 | F49: =IF(C49>=1,VLOOKUP(R48+MAX(0,R49-R48-C49)+0,药材收益口径!$H$2:$I$222,2,FALSE),0)+IF(C49>=2,VLOOKUP(R48+MAX(0,R49-R48-C49)+1,药材收益口径!$H$2:$I$222,2,FALSE),0)+IF(C49>=3,VLOOKUP(R48+MAX(0,R49-R48-C49)+2,药材收益口径!$H$2:$I$222,2,FALSE),0)+IF(C49>=4,VLOOKUP(R48+MAX(0,R49-R48-C49)+3,药材收益口径!$H$2:$I$222,2,FALSE),0) -> 596.60946 | G49: 460.8 | H49: 0 | I49: 0 | J49: =SUM(D49:I49) -> 5057.4095 | K49: =K48+J49 -> 209285.87 | L49: 3376.4 | M49: =M48+L49 -> 136983.6 | N49: =J49-L49 -> 1681.0095 | O49: =K49-M49 -> 72302.265 | P49: =20000+O49 -> 92302.265 | Q49: 2880 | R49: 195

Sheet 汇总
A1: 难度 | B1: 每天妙手回春 | C1: 李言闻/节气 | D1: 谢飞燕两笔触发 | E1: 世子触发 | F1: 前两年剧情银钱合计 | G1: 第一年收入 | H1: 第一年支出 | I1: 第一年收支差 | J1: 第一年末余额 | K1: 两年总收入 | L1: 两年总支出 | M1: 两年收支差 | N1: 两年末余额 | O1: 最低余额 | P1: 最低点
A2: 简单 | B2: 2 | C2: 1000 | D2: 第1年冬至、第1年大寒 | E2: 第2年惊蛰 | F2: =SUM(简单!I2:I49) -> 6000 | G2: =SUM(简单!J2:J25) -> 58995.261 | H2: =SUM(简单!L2:L25) -> 67166.8 | I2: =G2-H2 -> -8171.5393 | J2: =20000+I2 -> 11828.461 | K2: =SUM(简单!J2:J49) -> 140143.86 | L2: =SUM(简单!L2:L49) -> 136983.6 | M2: =K2-L2 -> 3160.2608 | N2: =20000+M2 -> 23160.261 | O2: =MIN(简单!P2:P49) -> 2843.8259 | P2: ="第"&INDEX(简单!A2:A49,MATCH(O2,简单!P2:P49,0))&"年"&INDEX(简单!B2:B49,MATCH(O2,简单!P2:P49,0)) -> 第1年秋分
A3: 普通 | B3: 3 | C3: 500 | D3: 第1年秋分、第1年寒露 | E3: 第1年小雪 | F3: =SUM(普通!I2:I49) -> 7000 | G3: =SUM(普通!J2:J25) -> 62109.958 | H3: =SUM(普通!L2:L25) -> 67166.8 | I3: =G3-H3 -> -5056.8417 | J3: =20000+I3 -> 14943.158 | K3: =SUM(普通!J2:J49) -> 172056.89 | L3: =SUM(普通!L2:L49) -> 136983.6 | M3: =K3-L3 -> 35073.295 | N3: =20000+M3 -> 55073.295 | O3: =MIN(普通!P2:P49) -> 2513.8871 | P3: ="第"&INDEX(普通!A2:A49,MATCH(O3,普通!P2:P49,0))&"年"&INDEX(普通!B2:B49,MATCH(O3,普通!P2:P49,0)) -> 第1年秋分
A4: 困难 | B4: 4 | C4: 0 | D4: 第1年大暑、第1年立秋 | E4: 第1年白露 | F4: =SUM(困难!I2:I49) -> 8000 | G4: =SUM(困难!J2:J25) -> 68410.325 | H4: =SUM(困难!L2:L25) -> 67166.8 | I4: =G4-H4 -> 1243.525 | J4: =20000+I4 -> 21243.525 | K4: =SUM(困难!J2:J49) -> 209285.87 | L4: =SUM(困难!L2:L49) -> 136983.6 | M4: =K4-L4 -> 72302.265 | N4: =20000+M4 -> 92302.265 | O4: =MIN(困难!P2:P49) -> 2532.2245 | P4: ="第"&INDEX(困难!A2:A49,MATCH(O4,困难!P2:P49,0))&"年"&INDEX(困难!B2:B49,MATCH(O4,困难!P2:P49,0)) -> 第1年小暑
A7: 难度 | B7: 剧情 | C7: 触发节气 | D7: 银钱奖励 | E7: 名望/心得影响 | F7: 说明
A8: 简单 | B8: 022_02 敬亭治疗成功（项目数据：柳敬亭） | C8: 第1年芒种 | D8: 1000 | F8: 按本次用户要求补充+1000文
A9: 简单 | B9: 023_02 谢飞燕肺气虚 | C9: 第1年冬至 | D9: 1000 | F9: 同一节气若有多个剧情，奖励合并计入该节气
A10: 简单 | B10: 024_02 谢飞燕肺阴虚 | C10: 第1年大寒 | D10: 1000 | F10: 同一节气若有多个剧情，奖励合并计入该节气
A11: 简单 | B11: 024_04 王百堂来访（心得+7）；005_02 治愈世子（银钱+1000，名望+1000） | C11: 第2年惊蛰 | D11: 1000 | E11: 名望+1000、心得+7 | F11: 同一节气若有多个剧情，奖励合并计入该节气
A12: 简单 | B12: 025_02 和尚肾精不足 | C12: 第2年大寒 | D12: 2000 | F12: 同一节气若有多个剧情，奖励合并计入该节气
A13: 普通 | B13: 022_02 敬亭治疗成功（项目数据：柳敬亭） | C13: 第1年立夏 | D13: 1000 | F13: 按本次用户要求补充+1000文
A14: 普通 | B14: 023_02 谢飞燕肺气虚 | C14: 第1年秋分 | D14: 1000 | F14: 同一节气若有多个剧情，奖励合并计入该节气
A15: 普通 | B15: 024_02 谢飞燕肺阴虚 | C15: 第1年寒露 | D15: 1000 | F15: 同一节气若有多个剧情，奖励合并计入该节气
A16: 普通 | B16: 024_04 王百堂来访（心得+7）；005_02 治愈世子（银钱+1000，名望+1000） | C16: 第1年小雪 | D16: 1000 | E16: 名望+1000、心得+7 | F16: 同一节气若有多个剧情，奖励合并计入该节气
A17: 普通 | B17: 025_02 和尚肾精不足 | C17: 第2年芒种 | D17: 2000 | F17: 同一节气若有多个剧情，奖励合并计入该节气
A18: 普通 | B18: 014_02 沈修文治疗成功 | C18: 第2年小雪 | D18: 1000 | F18: 同一节气若有多个剧情，奖励合并计入该节气
A19: 困难 | B19: 022_02 敬亭治疗成功（项目数据：柳敬亭） | C19: 第1年谷雨 | D19: 1000 | F19: 按本次用户要求补充+1000文
A20: 困难 | B20: 023_02 谢飞燕肺气虚 | C20: 第1年大暑 | D20: 1000 | F20: 同一节气若有多个剧情，奖励合并计入该节气
A21: 困难 | B21: 024_02 谢飞燕肺阴虚 | C21: 第1年立秋 | D21: 1000 | F21: 同一节气若有多个剧情，奖励合并计入该节气
A22: 困难 | B22: 005_02 治愈世子 | C22: 第1年白露 | D22: 1000 | E22: 名望+1000 | F22: 同一节气若有多个剧情，奖励合并计入该节气
A23: 困难 | B23: 024_04 王百堂来访 | C23: 第1年秋分 | D23: 0 | E23: 心得+7 | F23: 同一节气若有多个剧情，奖励合并计入该节气
A24: 困难 | B24: 025_02 和尚肾精不足 | C24: 第2年立春 | D24: 2000 | F24: 同一节气若有多个剧情，奖励合并计入该节气
A25: 困难 | B25: 014_02 沈修文治疗成功 | C25: 第2年立秋 | D25: 1000 | F25: 同一节气若有多个剧情，奖励合并计入该节气
A26: 困难 | B26: 017_02 杨善泉治疗成功 | C26: 第2年霜降 | D26: 1000 | F26: 同一节气若有多个剧情，奖励合并计入该节气

Sheet 药材收益口径
A1: 解锁心得阈值 | B1: 方剂 | C1: 标准病证 | D1: 单剂净收益（文） | E1: 解锁后累计方剂数 | F1: 解锁后随机病人药材净收益均值（文） | H1: 当前心得 | I1: 随机病人药材净收益期望/次（文） | J1: 已解锁方剂数 | L1: 口径说明 | M1: 内容
A2: 0 | B2: 桂枝汤 | C2: 风寒表虚证 | D2: 26 | E2: 3 | F2: 19.666667 | H2: 0 | I2: 19.666667 | J2: 3 | L2: 随机病人疾病池 | M2: 每次生成 random NPC 时，从当前已解锁疾病中随机抽取
A3: 0 | B3: 桂枝甘草汤 | C3: 心阳虚 | D3: 12 | E3: 3 | F3: 19.666667 | H3: 1 | I3: 19.666667 | J3: 3 | L3: 方剂解锁 | M3: 按所需药材的最高心得阈值；假设条目解锁后及时阅读药材
A4: 0 | B4: 麻黄汤 | C4: 风寒表实证 | D4: 21 | E4: 3 | F4: 19.666667 | H4: 2 | I4: 19.666667 | J4: 3 | L4: 心得更新 | M4: 每次妙手回春 +1；下一名病人立即使用更新后的解锁池
A5: 9 | B5: 银翘散 | C5: 风热表证 | D5: 218 | E5: 4 | F5: 69.25 | H5: 3 | I5: 19.666667 | J5: 3 | L5: 妊娠限制 | M5: 妊娠仅女性18–50岁 random NPC 可抽取；当前模板占比 17/51
A6: 14 | B6: 桑杏汤 | C6: 温燥证 | D6: 29.5 | E6: 5 | F6: 61.3 | H6: 4 | I6: 19.666667 | J6: 3
A7: 19 | B7: 二陈汤 | C7: 痰湿阻肺 | D7: 42 | E7: 6 | F7: 58.083333 | H7: 5 | I7: 19.666667 | J7: 3
A8: 20 | B8: 杏苏散 | C8: 凉燥证 | D8: 68 | E8: 7 | F8: 59.5 | H8: 6 | I8: 19.666667 | J8: 3
A9: 23 | B9: 玉屏风散 | C9: 卫气虚 | D9: 100 | E9: 8 | F9: 64.5625 | H9: 7 | I9: 19.666667 | J9: 3
A10: 25 | B10: 乌头汤 | C10: 痛痹 | D10: 688 | E10: 9 | F10: 133.83333 | H10: 8 | I10: 19.666667 | J10: 3
A11: 26 | B11: 大青龙汤 | C11: 表寒里热 | D11: 54 | E11: 11 | F11: 117.13636 | H11: 9 | I11: 69.25 | J11: 4
A12: 26 | B12: 麻杏石甘汤 | C12: 肺热壅盛 | D12: 30 | E12: 11 | F12: 117.13636 | H12: 10 | I12: 69.25 | J12: 4
A13: 28 | B13: 白虎桂枝汤 | C13: 热痹 | D13: 61 | E13: 13 | F13: 107.73077 | H13: 11 | I13: 69.25 | J13: 4
A14: 28 | B14: 白虎汤 | C14: 气分热盛 | D14: 51 | E14: 13 | F14: 107.73077 | H14: 12 | I14: 69.25 | J14: 4
A15: 33 | B15: 薏苡仁汤 | C15: 着痹 | D15: 87 | E15: 14 | F15: 106.25 | H15: 13 | I15: 69.25 | J15: 4
A16: 35 | B16: 防风汤 | C16: 行痹 | D16: 74 | E16: 15 | F16: 104.1 | H16: 14 | I16: 61.3 | J16: 5
A17: 36 | B17: 四君子汤 | C17: 脾气虚 | D17: 149 | E17: 16 | F17: 106.90625 | H17: 15 | I17: 61.3 | J17: 5
... A49: 107 | B49: 黄连阿胶汤 | C49: 心肾不交 | D49: 132 | E49: 48 | F49: 149.15236 | H49: 47 | I49: 104.97368 | J49: 19
H50: 48 | I50: 119.725 | J50: 20
H51: 49 | I51: 123.54762 | J51: 21
H52: 50 | I52: 121.02273 | J52: 22
H53: 51 | I53: 121.02273 | J53: 22
H54: 52 | I54: 116.97826 | J54: 23
H55: 53 | I55: 116.97826 | J55: 23
H56: 54 | I56: 116.97826 | J56: 23
H57: 55 | I57: 122.97917 | J57: 24
H58: 56 | I58: 122.97917 | J58: 24
H59: 57 | I59: 122.97917 | J59: 24
H60: 58 | I60: 124.5 | J60: 25
H61: 59 | I61: 121.82692 | J61: 26
... H222: 220 | I222: 149.15236 | J222: 48
